Classfile jar:file:/E:/Isuth/modDev/libs/AncientSpellcraft-1.12.2-1.8.1.jar!/com/windanesz/ancientspellcraft/item/ItemBattlemageShield.class
  Last modified Oct 21, 2025; size 19415 bytes
  MD5 checksum e159bef2377cff70e039a67011c2e3ed
  Compiled from "ItemBattlemageShield.java"
public class com.windanesz.ancientspellcraft.item.ItemBattlemageShield extends net.minecraft.item.Item implements electroblob.wizardry.item.ISpellCastingItem,electroblob.wizardry.item.IManaStoringItem,electroblob.wizardry.item.IWorkbenchItem,com.windanesz.ancientspellcraft.item.IItemWithSlots
  minor version: 0
  major version: 52
  flags: ACC_PUBLIC, ACC_SUPER
Constant pool:
    #1 = Utf8               com/windanesz/ancientspellcraft/item/ItemBattlemageShield
    #2 = Class              #1            // com/windanesz/ancientspellcraft/item/ItemBattlemageShield
    #3 = Utf8               net/minecraft/item/Item
    #4 = Class              #3            // net/minecraft/item/Item
    #5 = Utf8               electroblob/wizardry/item/ISpellCastingItem
    #6 = Class              #5            // electroblob/wizardry/item/ISpellCastingItem
    #7 = Utf8               electroblob/wizardry/item/IManaStoringItem
    #8 = Class              #7            // electroblob/wizardry/item/IManaStoringItem
    #9 = Utf8               electroblob/wizardry/item/IWorkbenchItem
   #10 = Class              #9            // electroblob/wizardry/item/IWorkbenchItem
   #11 = Utf8               com/windanesz/ancientspellcraft/item/IItemWithSlots
   #12 = Class              #11           // com/windanesz/ancientspellcraft/item/IItemWithSlots
   #13 = Utf8               ItemBattlemageShield.java
   #14 = Utf8               com/windanesz/ancientspellcraft/item/ItemBattlemageShield$1
   #15 = Class              #14           // com/windanesz/ancientspellcraft/item/ItemBattlemageShield$1
   #16 = Utf8               electroblob/wizardry/event/SpellCastEvent$Post
   #17 = Class              #16           // electroblob/wizardry/event/SpellCastEvent$Post
   #18 = Utf8               electroblob/wizardry/event/SpellCastEvent
   #19 = Class              #18           // electroblob/wizardry/event/SpellCastEvent
   #20 = Utf8               Post
   #21 = Utf8               electroblob/wizardry/packet/PacketCastSpell$Message
   #22 = Class              #21           // electroblob/wizardry/packet/PacketCastSpell$Message
   #23 = Utf8               electroblob/wizardry/packet/PacketCastSpell
   #24 = Class              #23           // electroblob/wizardry/packet/PacketCastSpell
   #25 = Utf8               Message
   #26 = Utf8               com/windanesz/ancientspellcraft/Settings$GeneralSettings
   #27 = Class              #26           // com/windanesz/ancientspellcraft/Settings$GeneralSettings
   #28 = Utf8               com/windanesz/ancientspellcraft/Settings
   #29 = Class              #28           // com/windanesz/ancientspellcraft/Settings
   #30 = Utf8               GeneralSettings
   #31 = Utf8               electroblob/wizardry/item/ItemWizardArmour$ArmourClass
   #32 = Class              #31           // electroblob/wizardry/item/ItemWizardArmour$ArmourClass
   #33 = Utf8               electroblob/wizardry/item/ItemWizardArmour
   #34 = Class              #33           // electroblob/wizardry/item/ItemWizardArmour
   #35 = Utf8               ArmourClass
   #36 = Utf8               electroblob/wizardry/event/SpellCastEvent$Source
   #37 = Class              #36           // electroblob/wizardry/event/SpellCastEvent$Source
   #38 = Utf8               Source
   #39 = Utf8               SHIELD_ARMOR_BONUS
   #40 = Utf8               Ljava/util/UUID;
   #41 = Utf8               SHIELD_ARMOR_PERCENT_BONUS
   #42 = Utf8               SHIELD_TOUGHNESS_BONUS
   #43 = Utf8               <init>
   #44 = Utf8               ()V
   #45 = NameAndType        #43:#44       // "<init>":()V
   #46 = Methodref          #4.#45        // net/minecraft/item/Item."<init>":()V
   #47 = Utf8               func_77664_n
   #48 = Utf8               ()Lnet/minecraft/item/Item;
   #49 = NameAndType        #47:#48       // func_77664_n:()Lnet/minecraft/item/Item;
   #50 = Methodref          #2.#49        // com/windanesz/ancientspellcraft/item/ItemBattlemageShield.func_77664_n:()Lnet/minecraft/item/Item;
   #51 = Utf8               field_77777_bU
   #52 = Utf8               I
   #53 = NameAndType        #51:#52       // field_77777_bU:I
   #54 = Fieldref           #2.#53        // com/windanesz/ancientspellcraft/item/ItemBattlemageShield.field_77777_bU:I
   #55 = Utf8               com/windanesz/ancientspellcraft/registry/ASTabs
   #56 = Class              #55           // com/windanesz/ancientspellcraft/registry/ASTabs
   #57 = Utf8               ANCIENTSPELLCRAFT_GEAR
   #58 = Utf8               Lnet/minecraft/creativetab/CreativeTabs;
   #59 = NameAndType        #57:#58       // ANCIENTSPELLCRAFT_GEAR:Lnet/minecraft/creativetab/CreativeTabs;
   #60 = Fieldref           #56.#59       // com/windanesz/ancientspellcraft/registry/ASTabs.ANCIENTSPELLCRAFT_GEAR:Lnet/minecraft/creativetab/CreativeTabs;
   #61 = Utf8               func_77637_a
   #62 = Utf8               (Lnet/minecraft/creativetab/CreativeTabs;)Lnet/minecraft/item/Item;
   #63 = NameAndType        #61:#62       // func_77637_a:(Lnet/minecraft/creativetab/CreativeTabs;)Lnet/minecraft/item/Item;
   #64 = Methodref          #2.#63        // com/windanesz/ancientspellcraft/item/ItemBattlemageShield.func_77637_a:(Lnet/minecraft/creativetab/CreativeTabs;)Lnet/minecraft/item/Item;
   #65 = Utf8               generalSettings
   #66 = Utf8               Lcom/windanesz/ancientspellcraft/Settings$GeneralSettings;
   #67 = NameAndType        #65:#66       // generalSettings:Lcom/windanesz/ancientspellcraft/Settings$GeneralSettings;
   #68 = Fieldref           #29.#67       // com/windanesz/ancientspellcraft/Settings.generalSettings:Lcom/windanesz/ancientspellcraft/Settings$GeneralSettings;
   #69 = Utf8               runic_shield_durability
   #70 = NameAndType        #69:#52       // runic_shield_durability:I
   #71 = Fieldref           #27.#70       // com/windanesz/ancientspellcraft/Settings$GeneralSettings.runic_shield_durability:I
   #72 = Utf8               func_77656_e
   #73 = Utf8               (I)Lnet/minecraft/item/Item;
   #74 = NameAndType        #72:#73       // func_77656_e:(I)Lnet/minecraft/item/Item;
   #75 = Methodref          #2.#74        // com/windanesz/ancientspellcraft/item/ItemBattlemageShield.func_77656_e:(I)Lnet/minecraft/item/Item;
   #76 = Utf8               net/minecraft/util/ResourceLocation
   #77 = Class              #76           // net/minecraft/util/ResourceLocation
   #78 = Utf8               blocking
   #79 = String             #78           // blocking
   #80 = Utf8               (Ljava/lang/String;)V
   #81 = NameAndType        #43:#80       // "<init>":(Ljava/lang/String;)V
   #82 = Methodref          #77.#81       // net/minecraft/util/ResourceLocation."<init>":(Ljava/lang/String;)V
   #83 = Utf8               (Lcom/windanesz/ancientspellcraft/item/ItemBattlemageShield;)V
   #84 = NameAndType        #43:#83       // "<init>":(Lcom/windanesz/ancientspellcraft/item/ItemBattlemageShield;)V
   #85 = Methodref          #15.#84       // com/windanesz/ancientspellcraft/item/ItemBattlemageShield$1."<init>":(Lcom/windanesz/ancientspellcraft/item/ItemBattlemageShield;)V
   #86 = Utf8               func_185043_a
   #87 = Utf8               (Lnet/minecraft/util/ResourceLocation;Lnet/minecraft/item/IItemPropertyGetter;)V
   #88 = NameAndType        #86:#87       // func_185043_a:(Lnet/minecraft/util/ResourceLocation;Lnet/minecraft/item/IItemPropertyGetter;)V
   #89 = Methodref          #2.#88        // com/windanesz/ancientspellcraft/item/ItemBattlemageShield.func_185043_a:(Lnet/minecraft/util/ResourceLocation;Lnet/minecraft/item/IItemPropertyGetter;)V
   #90 = Utf8               net/minecraft/block/BlockDispenser
   #91 = Class              #90           // net/minecraft/block/BlockDispenser
   #92 = Utf8               field_149943_a
   #93 = Utf8               Lnet/minecraft/util/registry/RegistryDefaulted;
   #94 = NameAndType        #92:#93       // field_149943_a:Lnet/minecraft/util/registry/RegistryDefaulted;
   #95 = Fieldref           #91.#94       // net/minecraft/block/BlockDispenser.field_149943_a:Lnet/minecraft/util/registry/RegistryDefaulted;
   #96 = Utf8               net/minecraft/item/ItemArmor
   #97 = Class              #96           // net/minecraft/item/ItemArmor
   #98 = Utf8               field_96605_cw
   #99 = Utf8               Lnet/minecraft/dispenser/IBehaviorDispenseItem;
  #100 = NameAndType        #98:#99       // field_96605_cw:Lnet/minecraft/dispenser/IBehaviorDispenseItem;
  #101 = Fieldref           #97.#100      // net/minecraft/item/ItemArmor.field_96605_cw:Lnet/minecraft/dispenser/IBehaviorDispenseItem;
  #102 = Utf8               net/minecraft/util/registry/RegistryDefaulted
  #103 = Class              #102          // net/minecraft/util/registry/RegistryDefaulted
  #104 = Utf8               func_82595_a
  #105 = Utf8               (Ljava/lang/Object;Ljava/lang/Object;)V
  #106 = NameAndType        #104:#105     // func_82595_a:(Ljava/lang/Object;Ljava/lang/Object;)V
  #107 = Methodref          #103.#106     // net/minecraft/util/registry/RegistryDefaulted.func_82595_a:(Ljava/lang/Object;Ljava/lang/Object;)V
  #108 = Utf8               electroblob/wizardry/registry/WizardryRecipes
  #109 = Class              #108          // electroblob/wizardry/registry/WizardryRecipes
  #110 = Utf8               addToManaFlaskCharging
  #111 = Utf8               (Lnet/minecraft/item/Item;)V
  #112 = NameAndType        #110:#111     // addToManaFlaskCharging:(Lnet/minecraft/item/Item;)V
  #113 = Methodref          #109.#112     // electroblob/wizardry/registry/WizardryRecipes.addToManaFlaskCharging:(Lnet/minecraft/item/Item;)V
  #114 = Utf8               this
  #115 = Utf8               Lcom/windanesz/ancientspellcraft/item/ItemBattlemageShield;
  #116 = Utf8               getSpellSlotCount
  #117 = Utf8               (Lnet/minecraft/item/ItemStack;)I
  #118 = Utf8               stack
  #119 = Utf8               Lnet/minecraft/item/ItemStack;
  #120 = Utf8               onApplyButtonPressed
  #121 = Utf8               (Lnet/minecraft/entity/player/EntityPlayer;Lnet/minecraft/inventory/Slot;Lnet/minecraft/inventory/Slot;Lnet/minecraft/inventory/Slot;[Lnet/minecraft/inventory/Slot;)Z
  #122 = Utf8               net/minecraft/inventory/Slot
  #123 = Class              #122          // net/minecraft/inventory/Slot
  #124 = Utf8               func_75216_d
  #125 = Utf8               ()Z
  #126 = NameAndType        #124:#125     // func_75216_d:()Z
  #127 = Methodref          #123.#126     // net/minecraft/inventory/Slot.func_75216_d:()Z
  #128 = Utf8               func_75211_c
  #129 = Utf8               ()Lnet/minecraft/item/ItemStack;
  #130 = NameAndType        #128:#129     // func_75211_c:()Lnet/minecraft/item/ItemStack;
  #131 = Methodref          #123.#130     // net/minecraft/inventory/Slot.func_75211_c:()Lnet/minecraft/item/ItemStack;
  #132 = Utf8               net/minecraft/item/ItemStack
  #133 = Class              #132          // net/minecraft/item/ItemStack
  #134 = Utf8               func_77946_l
  #135 = NameAndType        #134:#129     // func_77946_l:()Lnet/minecraft/item/ItemStack;
  #136 = Methodref          #133.#135     // net/minecraft/item/ItemStack.func_77946_l:()Lnet/minecraft/item/ItemStack;
  #137 = Utf8               applyUpgrade
  #138 = Utf8               (Lnet/minecraft/entity/player/EntityPlayer;Lnet/minecraft/item/ItemStack;Lnet/minecraft/item/ItemStack;)Lnet/minecraft/item/ItemStack;
  #139 = NameAndType        #137:#138     // applyUpgrade:(Lnet/minecraft/entity/player/EntityPlayer;Lnet/minecraft/item/ItemStack;Lnet/minecraft/item/ItemStack;)Lnet/minecraft/item/ItemStack;
  #140 = Methodref          #2.#139       // com/windanesz/ancientspellcraft/item/ItemBattlemageShield.applyUpgrade:(Lnet/minecraft/entity/player/EntityPlayer;Lnet/minecraft/item/ItemStack;Lnet/minecraft/item/ItemStack;)Lnet/minecraft/item/ItemStack;
  #141 = Utf8               func_75215_d
  #142 = Utf8               (Lnet/minecraft/item/ItemStack;)V
  #143 = NameAndType        #141:#142     // func_75215_d:(Lnet/minecraft/item/ItemStack;)V
  #144 = Methodref          #123.#143     // net/minecraft/inventory/Slot.func_75215_d:(Lnet/minecraft/item/ItemStack;)V
  #145 = Utf8               func_77989_b
  #146 = Utf8               (Lnet/minecraft/item/ItemStack;Lnet/minecraft/item/ItemStack;)Z
  #147 = NameAndType        #145:#146     // func_77989_b:(Lnet/minecraft/item/ItemStack;Lnet/minecraft/item/ItemStack;)Z
  #148 = Methodref          #133.#147     // net/minecraft/item/ItemStack.func_77989_b:(Lnet/minecraft/item/ItemStack;Lnet/minecraft/item/ItemStack;)Z
  #149 = Utf8               field_190927_a
  #150 = NameAndType        #149:#119     // field_190927_a:Lnet/minecraft/item/ItemStack;
  #151 = Fieldref           #133.#150     // net/minecraft/item/ItemStack.field_190927_a:Lnet/minecraft/item/ItemStack;
  #152 = Utf8               isManaFull
  #153 = Utf8               (Lnet/minecraft/item/ItemStack;)Z
  #154 = NameAndType        #152:#153     // isManaFull:(Lnet/minecraft/item/ItemStack;)Z
  #155 = Methodref          #2.#154       // com/windanesz/ancientspellcraft/item/ItemBattlemageShield.isManaFull:(Lnet/minecraft/item/ItemStack;)Z
  #156 = Utf8               getManaCapacity
  #157 = NameAndType        #156:#117     // getManaCapacity:(Lnet/minecraft/item/ItemStack;)I
  #158 = Methodref          #2.#157       // com/windanesz/ancientspellcraft/item/ItemBattlemageShield.getManaCapacity:(Lnet/minecraft/item/ItemStack;)I
  #159 = Utf8               getMana
  #160 = NameAndType        #159:#117     // getMana:(Lnet/minecraft/item/ItemStack;)I
  #161 = Methodref          #2.#160       // com/windanesz/ancientspellcraft/item/ItemBattlemageShield.getMana:(Lnet/minecraft/item/ItemStack;)I
  #162 = Utf8               func_190916_E
  #163 = Utf8               ()I
  #164 = NameAndType        #162:#163     // func_190916_E:()I
  #165 = Methodref          #133.#164     // net/minecraft/item/ItemStack.func_190916_E:()I
  #166 = Utf8               rechargeMana
  #167 = Utf8               (Lnet/minecraft/item/ItemStack;I)V
  #168 = NameAndType        #166:#167     // rechargeMana:(Lnet/minecraft/item/ItemStack;I)V
  #169 = Methodref          #2.#168       // com/windanesz/ancientspellcraft/item/ItemBattlemageShield.rechargeMana:(Lnet/minecraft/item/ItemStack;I)V
  #170 = Utf8               func_75209_a
  #171 = Utf8               (I)Lnet/minecraft/item/ItemStack;
  #172 = NameAndType        #170:#171     // func_75209_a:(I)Lnet/minecraft/item/ItemStack;
  #173 = Methodref          #123.#172     // net/minecraft/inventory/Slot.func_75209_a:(I)Lnet/minecraft/item/ItemStack;
  #174 = Utf8               setMana
  #175 = NameAndType        #174:#167     // setMana:(Lnet/minecraft/item/ItemStack;I)V
  #176 = Methodref          #2.#175       // com/windanesz/ancientspellcraft/item/ItemBattlemageShield.setMana:(Lnet/minecraft/item/ItemStack;I)V
  #177 = Double             100.0d
  #179 = Utf8               java/lang/Math
  #180 = Class              #179          // java/lang/Math
  #181 = Utf8               ceil
  #182 = Utf8               (D)D
  #183 = NameAndType        #181:#182     // ceil:(D)D
  #184 = Methodref          #180.#183     // java/lang/Math.ceil:(D)D
  #185 = Utf8               original
  #186 = Utf8               chargeDepleted
  #187 = Utf8               player
  #188 = Utf8               Lnet/minecraft/entity/player/EntityPlayer;
  #189 = Utf8               centre
  #190 = Utf8               Lnet/minecraft/inventory/Slot;
  #191 = Utf8               crystals
  #192 = Utf8               upgrade
  #193 = Utf8               spellBooks
  #194 = Utf8               [Lnet/minecraft/inventory/Slot;
  #195 = Utf8               changed
  #196 = Utf8               Z
  #197 = Utf8               getMaxDamage
  #198 = NameAndType        #197:#117     // getMaxDamage:(Lnet/minecraft/item/ItemStack;)I
  #199 = Methodref          #4.#198       // net/minecraft/item/Item.getMaxDamage:(Lnet/minecraft/item/ItemStack;)I
  #200 = Float              0.15f
  #201 = Utf8               electroblob/wizardry/registry/WizardryItems
  #202 = Class              #201          // electroblob/wizardry/registry/WizardryItems
  #203 = Utf8               storage_upgrade
  #204 = Utf8               Lnet/minecraft/item/Item;
  #205 = NameAndType        #203:#204     // storage_upgrade:Lnet/minecraft/item/Item;
  #206 = Fieldref           #202.#205     // electroblob/wizardry/registry/WizardryItems.storage_upgrade:Lnet/minecraft/item/Item;
  #207 = Utf8               electroblob/wizardry/util/WandHelper
  #208 = Class              #207          // electroblob/wizardry/util/WandHelper
  #209 = Utf8               getUpgradeLevel
  #210 = Utf8               (Lnet/minecraft/item/ItemStack;Lnet/minecraft/item/Item;)I
  #211 = NameAndType        #209:#210     // getUpgradeLevel:(Lnet/minecraft/item/ItemStack;Lnet/minecraft/item/Item;)I
  #212 = Methodref          #208.#211     // electroblob/wizardry/util/WandHelper.getUpgradeLevel:(Lnet/minecraft/item/ItemStack;Lnet/minecraft/item/Item;)I
  #213 = Float              0.5f
  #214 = Utf8               Ljavax/annotation/Nullable;
  #215 = Utf8               func_77973_b
  #216 = NameAndType        #215:#48      // func_77973_b:()Lnet/minecraft/item/Item;
  #217 = Methodref          #133.#216     // net/minecraft/item/ItemStack.func_77973_b:()Lnet/minecraft/item/Item;
  #218 = Utf8               isWandUpgrade
  #219 = Utf8               (Lnet/minecraft/item/Item;)Z
  #220 = NameAndType        #218:#219     // isWandUpgrade:(Lnet/minecraft/item/Item;)Z
  #221 = Methodref          #208.#220     // electroblob/wizardry/util/WandHelper.isWandUpgrade:(Lnet/minecraft/item/Item;)Z
  #222 = Utf8               siphon_upgrade
  #223 = NameAndType        #222:#204     // siphon_upgrade:Lnet/minecraft/item/Item;
  #224 = Fieldref           #202.#223     // electroblob/wizardry/registry/WizardryItems.siphon_upgrade:Lnet/minecraft/item/Item;
  #225 = Utf8               condenser_upgrade
  #226 = NameAndType        #225:#204     // condenser_upgrade:Lnet/minecraft/item/Item;
  #227 = Fieldref           #202.#226     // electroblob/wizardry/registry/WizardryItems.condenser_upgrade:Lnet/minecraft/item/Item;
  #228 = Utf8               com/windanesz/ancientspellcraft/registry/ASItems
  #229 = Class              #228          // com/windanesz/ancientspellcraft/registry/ASItems
  #230 = Utf8               soulbound_upgrade
  #231 = NameAndType        #230:#204     // soulbound_upgrade:Lnet/minecraft/item/Item;
  #232 = Fieldref           #229.#231     // com/windanesz/ancientspellcraft/registry/ASItems.soulbound_upgrade:Lnet/minecraft/item/Item;
  #233 = Utf8               getTotalUpgrades
  #234 = NameAndType        #233:#117     // getTotalUpgrades:(Lnet/minecraft/item/ItemStack;)I
  #235 = Methodref          #208.#234     // electroblob/wizardry/util/WandHelper.getTotalUpgrades:(Lnet/minecraft/item/ItemStack;)I
  #236 = Utf8               (Lnet/minecraft/item/ItemStack;Lnet/minecraft/item/Item;)V
  #237 = NameAndType        #137:#236     // applyUpgrade:(Lnet/minecraft/item/ItemStack;Lnet/minecraft/item/Item;)V
  #238 = Methodref          #208.#237     // electroblob/wizardry/util/WandHelper.applyUpgrade:(Lnet/minecraft/item/ItemStack;Lnet/minecraft/item/Item;)V
  #239 = Utf8               func_190918_g
  #240 = Utf8               (I)V
  #241 = NameAndType        #239:#240     // func_190918_g:(I)V
  #242 = Methodref          #133.#241     // net/minecraft/item/ItemStack.func_190918_g:(I)V
  #243 = Utf8               electroblob/wizardry/registry/WizardryAdvancementTriggers
  #244 = Class              #243          // electroblob/wizardry/registry/WizardryAdvancementTriggers
  #245 = Utf8               special_upgrade
  #246 = Utf8               Lelectroblob/wizardry/advancement/CustomAdvancementTrigger;
  #247 = NameAndType        #245:#246     // special_upgrade:Lelectroblob/wizardry/advancement/CustomAdvancementTrigger;
  #248 = Fieldref           #244.#247     // electroblob/wizardry/registry/WizardryAdvancementTriggers.special_upgrade:Lelectroblob/wizardry/advancement/CustomAdvancementTrigger;
  #249 = Utf8               electroblob/wizardry/advancement/CustomAdvancementTrigger
  #250 = Class              #249          // electroblob/wizardry/advancement/CustomAdvancementTrigger
  #251 = Utf8               triggerFor
  #252 = Utf8               (Lnet/minecraft/entity/player/EntityPlayer;)V
  #253 = NameAndType        #251:#252     // triggerFor:(Lnet/minecraft/entity/player/EntityPlayer;)V
  #254 = Methodref          #250.#253     // electroblob/wizardry/advancement/CustomAdvancementTrigger.triggerFor:(Lnet/minecraft/entity/player/EntityPlayer;)V
  #255 = Utf8               prevMana
  #256 = Utf8               maxUpgrades
  #257 = Utf8               specialUpgrade
  #258 = Utf8               shield
  #259 = Utf8               showTooltip
  #260 = Utf8               getDamage
  #261 = NameAndType        #260:#117     // getDamage:(Lnet/minecraft/item/ItemStack;)I
  #262 = Methodref          #2.#261       // com/windanesz/ancientspellcraft/item/ItemBattlemageShield.getDamage:(Lnet/minecraft/item/ItemStack;)I
  #263 = Utf8               setDamage
  #264 = NameAndType        #263:#167     // setDamage:(Lnet/minecraft/item/ItemStack;I)V
  #265 = Methodref          #4.#264       // net/minecraft/item/Item.setDamage:(Lnet/minecraft/item/ItemStack;I)V
  #266 = Utf8               damage
  #267 = Utf8               mana
  #268 = Methodref          #2.#198       // com/windanesz/ancientspellcraft/item/ItemBattlemageShield.getMaxDamage:(Lnet/minecraft/item/ItemStack;)I
  #269 = Utf8               func_77624_a
  #270 = Utf8               (Lnet/minecraft/item/ItemStack;Lnet/minecraft/world/World;Ljava/util/List;Lnet/minecraft/client/util/ITooltipFlag;)V
  #271 = Utf8               (Lnet/minecraft/item/ItemStack;Lnet/minecraft/world/World;Ljava/util/List<Ljava/lang/String;>;Lnet/minecraft/client/util/ITooltipFlag;)V
  #272 = Utf8               Lnet/minecraftforge/fml/relauncher/SideOnly;
  #273 = Utf8               value
  #274 = Utf8               Lnet/minecraftforge/fml/relauncher/Side;
  #275 = Utf8               CLIENT
  #276 = Utf8               electroblob/wizardry/Wizardry
  #277 = Class              #276          // electroblob/wizardry/Wizardry
  #278 = Utf8               proxy
  #279 = Utf8               Lelectroblob/wizardry/CommonProxy;
  #280 = NameAndType        #278:#279     // proxy:Lelectroblob/wizardry/CommonProxy;
  #281 = Fieldref           #277.#280     // electroblob/wizardry/Wizardry.proxy:Lelectroblob/wizardry/CommonProxy;
  #282 = Utf8               java/lang/StringBuilder
  #283 = Class              #282          // java/lang/StringBuilder
  #284 = Methodref          #283.#45      // java/lang/StringBuilder."<init>":()V
  #285 = Utf8               item.
  #286 = String             #285          // item.
  #287 = Utf8               append
  #288 = Utf8               (Ljava/lang/String;)Ljava/lang/StringBuilder;
  #289 = NameAndType        #287:#288     // append:(Ljava/lang/String;)Ljava/lang/StringBuilder;
  #290 = Methodref          #283.#289     // java/lang/StringBuilder.append:(Ljava/lang/String;)Ljava/lang/StringBuilder;
  #291 = Utf8               getRegistryName
  #292 = Utf8               ()Lnet/minecraft/util/ResourceLocation;
  #293 = NameAndType        #291:#292     // getRegistryName:()Lnet/minecraft/util/ResourceLocation;
  #294 = Methodref          #2.#293       // com/windanesz/ancientspellcraft/item/ItemBattlemageShield.getRegistryName:()Lnet/minecraft/util/ResourceLocation;
  #295 = Utf8               (Ljava/lang/Object;)Ljava/lang/StringBuilder;
  #296 = NameAndType        #287:#295     // append:(Ljava/lang/Object;)Ljava/lang/StringBuilder;
  #297 = Methodref          #283.#296     // java/lang/StringBuilder.append:(Ljava/lang/Object;)Ljava/lang/StringBuilder;
  #298 = Utf8               .desc
  #299 = String             #298          // .desc
  #300 = Utf8               toString
  #301 = Utf8               ()Ljava/lang/String;
  #302 = NameAndType        #300:#301     // toString:()Ljava/lang/String;
  #303 = Methodref          #283.#302     // java/lang/StringBuilder.toString:()Ljava/lang/String;
  #304 = Utf8               java/lang/Object
  #305 = Class              #304          // java/lang/Object
  #306 = Utf8               electroblob/wizardry/CommonProxy
  #307 = Class              #306          // electroblob/wizardry/CommonProxy
  #308 = Utf8               addMultiLineDescription
  #309 = Utf8               (Ljava/util/List;Ljava/lang/String;[Ljava/lang/Object;)V
  #310 = NameAndType        #308:#309     // addMultiLineDescription:(Ljava/util/List;Ljava/lang/String;[Ljava/lang/Object;)V
  #311 = Methodref          #307.#310     // electroblob/wizardry/CommonProxy.addMultiLineDescription:(Ljava/util/List;Ljava/lang/String;[Ljava/lang/Object;)V
  #312 = Utf8               net/minecraft/client/util/ITooltipFlag
  #313 = Class              #312          // net/minecraft/client/util/ITooltipFlag
  #314 = Utf8               func_194127_a
  #315 = NameAndType        #314:#125     // func_194127_a:()Z
  #316 = InterfaceMethodref #313.#315     // net/minecraft/client/util/ITooltipFlag.func_194127_a:()Z
  #317 = Utf8               üś9
  #318 = String             #317          // üś9
  #319 = Utf8               item.ebwizardry:wand.mana
  #320 = String             #319          // item.ebwizardry:wand.mana
  #321 = Utf8               java/lang/Integer
  #322 = Class              #321          // java/lang/Integer
  #323 = Utf8               valueOf
  #324 = Utf8               (I)Ljava/lang/Integer;
  #325 = NameAndType        #323:#324     // valueOf:(I)Ljava/lang/Integer;
  #326 = Methodref          #322.#325     // java/lang/Integer.valueOf:(I)Ljava/lang/Integer;
  #327 = Utf8               net/minecraft/client/resources/I18n
  #328 = Class              #327          // net/minecraft/client/resources/I18n
  #329 = Utf8               func_135052_a
  #330 = Utf8               (Ljava/lang/String;[Ljava/lang/Object;)Ljava/lang/String;
  #331 = NameAndType        #329:#330     // func_135052_a:(Ljava/lang/String;[Ljava/lang/Object;)Ljava/lang/String;
  #332 = Methodref          #328.#331     // net/minecraft/client/resources/I18n.func_135052_a:(Ljava/lang/String;[Ljava/lang/Object;)Ljava/lang/String;
  #333 = Utf8               java/util/List
  #334 = Class              #333          // java/util/List
  #335 = Utf8               add
  #336 = Utf8               (Ljava/lang/Object;)Z
  #337 = NameAndType        #335:#336     // add:(Ljava/lang/Object;)Z
  #338 = InterfaceMethodref #334.#337     // java/util/List.add:(Ljava/lang/Object;)Z
  #339 = Utf8               worldIn
  #340 = Utf8               Lnet/minecraft/world/World;
  #341 = Utf8               tooltip
  #342 = Utf8               Ljava/util/List<Ljava/lang/String;>;
  #343 = Utf8               Ljava/util/List;
  #344 = Utf8               advanced
  #345 = Utf8               Lnet/minecraft/client/util/ITooltipFlag;
  #346 = Utf8               func_77661_b
  #347 = Utf8               (Lnet/minecraft/item/ItemStack;)Lnet/minecraft/item/EnumAction;
  #348 = Utf8               net/minecraft/item/EnumAction
  #349 = Class              #348          // net/minecraft/item/EnumAction
  #350 = Utf8               BLOCK
  #351 = Utf8               Lnet/minecraft/item/EnumAction;
  #352 = NameAndType        #350:#351     // BLOCK:Lnet/minecraft/item/EnumAction;
  #353 = Fieldref           #349.#352     // net/minecraft/item/EnumAction.BLOCK:Lnet/minecraft/item/EnumAction;
  #354 = Utf8               func_77626_a
  #355 = Utf8               func_77659_a
  #356 = Utf8               (Lnet/minecraft/world/World;Lnet/minecraft/entity/player/EntityPlayer;Lnet/minecraft/util/EnumHand;)Lnet/minecraft/util/ActionResult;
  #357 = Utf8               (Lnet/minecraft/world/World;Lnet/minecraft/entity/player/EntityPlayer;Lnet/minecraft/util/EnumHand;)Lnet/minecraft/util/ActionResult<Lnet/minecraft/item/ItemStack;>;
  #358 = Utf8               net/minecraft/entity/player/EntityPlayer
  #359 = Class              #358          // net/minecraft/entity/player/EntityPlayer
  #360 = Utf8               func_184586_b
  #361 = Utf8               (Lnet/minecraft/util/EnumHand;)Lnet/minecraft/item/ItemStack;
  #362 = NameAndType        #360:#361     // func_184586_b:(Lnet/minecraft/util/EnumHand;)Lnet/minecraft/item/ItemStack;
  #363 = Methodref          #359.#362     // net/minecraft/entity/player/EntityPlayer.func_184586_b:(Lnet/minecraft/util/EnumHand;)Lnet/minecraft/item/ItemStack;
  #364 = Utf8               isBattlemage
  #365 = Utf8               (Lnet/minecraft/entity/player/EntityPlayer;)Z
  #366 = NameAndType        #364:#365     // isBattlemage:(Lnet/minecraft/entity/player/EntityPlayer;)Z
  #367 = Methodref          #2.#366       // com/windanesz/ancientspellcraft/item/ItemBattlemageShield.isBattlemage:(Lnet/minecraft/entity/player/EntityPlayer;)Z
  #368 = Utf8               Only a battlemage can use this
  #369 = String             #368          // Only a battlemage can use this
  #370 = Utf8               com/windanesz/ancientspellcraft/util/ASUtils
  #371 = Class              #370          // com/windanesz/ancientspellcraft/util/ASUtils
  #372 = Utf8               sendMessage
  #373 = Utf8               (Lnet/minecraft/entity/Entity;Ljava/lang/String;Z[Ljava/lang/Object;)V
  #374 = NameAndType        #372:#373     // sendMessage:(Lnet/minecraft/entity/Entity;Ljava/lang/String;Z[Ljava/lang/Object;)V
  #375 = Methodref          #371.#374     // com/windanesz/ancientspellcraft/util/ASUtils.sendMessage:(Lnet/minecraft/entity/Entity;Ljava/lang/String;Z[Ljava/lang/Object;)V
  #376 = Utf8               net/minecraft/util/ActionResult
  #377 = Class              #376          // net/minecraft/util/ActionResult
  #378 = Utf8               net/minecraft/util/EnumActionResult
  #379 = Class              #378          // net/minecraft/util/EnumActionResult
  #380 = Utf8               FAIL
  #381 = Utf8               Lnet/minecraft/util/EnumActionResult;
  #382 = NameAndType        #380:#381     // FAIL:Lnet/minecraft/util/EnumActionResult;
  #383 = Fieldref           #379.#382     // net/minecraft/util/EnumActionResult.FAIL:Lnet/minecraft/util/EnumActionResult;
  #384 = Utf8               (Lnet/minecraft/util/EnumActionResult;Ljava/lang/Object;)V
  #385 = NameAndType        #43:#384      // "<init>":(Lnet/minecraft/util/EnumActionResult;Ljava/lang/Object;)V
  #386 = Methodref          #377.#385     // net/minecraft/util/ActionResult."<init>":(Lnet/minecraft/util/EnumActionResult;Ljava/lang/Object;)V
  #387 = Utf8               net/minecraft/util/EnumHand
  #388 = Class              #387          // net/minecraft/util/EnumHand
  #389 = Utf8               MAIN_HAND
  #390 = Utf8               Lnet/minecraft/util/EnumHand;
  #391 = NameAndType        #389:#390     // MAIN_HAND:Lnet/minecraft/util/EnumHand;
  #392 = Fieldref           #388.#391     // net/minecraft/util/EnumHand.MAIN_HAND:Lnet/minecraft/util/EnumHand;
  #393 = Utf8               func_70093_af
  #394 = NameAndType        #393:#125     // func_70093_af:()Z
  #395 = Methodref          #359.#394     // net/minecraft/entity/player/EntityPlayer.func_70093_af:()Z
  #396 = Utf8               com/windanesz/ancientspellcraft/AncientSpellcraft
  #397 = Class              #396          // com/windanesz/ancientspellcraft/AncientSpellcraft
  #398 = Utf8               instance
  #399 = Utf8               Lcom/windanesz/ancientspellcraft/AncientSpellcraft;
  #400 = NameAndType        #398:#399     // instance:Lcom/windanesz/ancientspellcraft/AncientSpellcraft;
  #401 = Fieldref           #397.#400     // com/windanesz/ancientspellcraft/AncientSpellcraft.instance:Lcom/windanesz/ancientspellcraft/AncientSpellcraft;
  #402 = Utf8               com/windanesz/ancientspellcraft/client/gui/GuiHandlerAS
  #403 = Class              #402          // com/windanesz/ancientspellcraft/client/gui/GuiHandlerAS
  #404 = Utf8               BATTLEMAGE_SHIELD
  #405 = NameAndType        #404:#52      // BATTLEMAGE_SHIELD:I
  #406 = Fieldref           #403.#405     // com/windanesz/ancientspellcraft/client/gui/GuiHandlerAS.BATTLEMAGE_SHIELD:I
  #407 = Utf8               field_70170_p
  #408 = NameAndType        #407:#340     // field_70170_p:Lnet/minecraft/world/World;
  #409 = Fieldref           #359.#408     // net/minecraft/entity/player/EntityPlayer.field_70170_p:Lnet/minecraft/world/World;
  #410 = Utf8               openGui
  #411 = Utf8               (Ljava/lang/Object;ILnet/minecraft/world/World;III)V
  #412 = NameAndType        #410:#411     // openGui:(Ljava/lang/Object;ILnet/minecraft/world/World;III)V
  #413 = Methodref          #359.#412     // net/minecraft/entity/player/EntityPlayer.openGui:(Ljava/lang/Object;ILnet/minecraft/world/World;III)V
  #414 = Utf8               SUCCESS
  #415 = NameAndType        #414:#381     // SUCCESS:Lnet/minecraft/util/EnumActionResult;
  #416 = Fieldref           #379.#415     // net/minecraft/util/EnumActionResult.SUCCESS:Lnet/minecraft/util/EnumActionResult;
  #417 = Utf8               newResult
  #418 = Utf8               (Lnet/minecraft/util/EnumActionResult;Ljava/lang/Object;)Lnet/minecraft/util/ActionResult;
  #419 = NameAndType        #417:#418     // newResult:(Lnet/minecraft/util/EnumActionResult;Ljava/lang/Object;)Lnet/minecraft/util/ActionResult;
  #420 = Methodref          #377.#419     // net/minecraft/util/ActionResult.newResult:(Lnet/minecraft/util/EnumActionResult;Ljava/lang/Object;)Lnet/minecraft/util/ActionResult;
  #421 = Utf8               isManaEmpty
  #422 = NameAndType        #421:#153     // isManaEmpty:(Lnet/minecraft/item/ItemStack;)Z
  #423 = Methodref          #2.#422       // com/windanesz/ancientspellcraft/item/ItemBattlemageShield.isManaEmpty:(Lnet/minecraft/item/ItemStack;)Z
  #424 = Utf8               func_184598_c
  #425 = Utf8               (Lnet/minecraft/util/EnumHand;)V
  #426 = NameAndType        #424:#425     // func_184598_c:(Lnet/minecraft/util/EnumHand;)V
  #427 = Methodref          #359.#426     // net/minecraft/entity/player/EntityPlayer.func_184598_c:(Lnet/minecraft/util/EnumHand;)V
  #428 = Utf8               hand
  #429 = Utf8               canContinueUsing
  #430 = Utf8               func_185132_d
  #431 = NameAndType        #430:#146     // func_185132_d:(Lnet/minecraft/item/ItemStack;Lnet/minecraft/item/ItemStack;)Z
  #432 = Methodref          #133.#431     // net/minecraft/item/ItemStack.func_185132_d:(Lnet/minecraft/item/ItemStack;Lnet/minecraft/item/ItemStack;)Z
  #433 = NameAndType        #429:#146     // canContinueUsing:(Lnet/minecraft/item/ItemStack;Lnet/minecraft/item/ItemStack;)Z
  #434 = Methodref          #4.#433       // net/minecraft/item/Item.canContinueUsing:(Lnet/minecraft/item/ItemStack;Lnet/minecraft/item/ItemStack;)Z
  #435 = Utf8               oldStack
  #436 = Utf8               newStack
  #437 = Utf8               onUsingTick
  #438 = Utf8               (Lnet/minecraft/item/ItemStack;Lnet/minecraft/entity/EntityLivingBase;I)V
  #439 = NameAndType        #437:#438     // onUsingTick:(Lnet/minecraft/item/ItemStack;Lnet/minecraft/entity/EntityLivingBase;I)V
  #440 = Methodref          #4.#439       // net/minecraft/item/Item.onUsingTick:(Lnet/minecraft/item/ItemStack;Lnet/minecraft/entity/EntityLivingBase;I)V
  #441 = Utf8               user
  #442 = Utf8               Lnet/minecraft/entity/EntityLivingBase;
  #443 = Utf8               count
  #444 = Utf8               BATTLEMAGE
  #445 = Utf8               Lelectroblob/wizardry/item/ItemWizardArmour$ArmourClass;
  #446 = NameAndType        #444:#445     // BATTLEMAGE:Lelectroblob/wizardry/item/ItemWizardArmour$ArmourClass;
  #447 = Fieldref           #32.#446      // electroblob/wizardry/item/ItemWizardArmour$ArmourClass.BATTLEMAGE:Lelectroblob/wizardry/item/ItemWizardArmour$ArmourClass;
  #448 = Utf8               com/windanesz/ancientspellcraft/util/WizardArmourUtils
  #449 = Class              #448          // com/windanesz/ancientspellcraft/util/WizardArmourUtils
  #450 = Utf8               isWearingFullSet
  #451 = Utf8               (Lnet/minecraft/entity/EntityLivingBase;Lelectroblob/wizardry/constants/Element;Lelectroblob/wizardry/item/ItemWizardArmour$ArmourClass;)Z
  #452 = NameAndType        #450:#451     // isWearingFullSet:(Lnet/minecraft/entity/EntityLivingBase;Lelectroblob/wizardry/constants/Element;Lelectroblob/wizardry/item/ItemWizardArmour$ArmourClass;)Z
  #453 = Methodref          #449.#452     // com/windanesz/ancientspellcraft/util/WizardArmourUtils.isWearingFullSet:(Lnet/minecraft/entity/EntityLivingBase;Lelectroblob/wizardry/constants/Element;Lelectroblob/wizardry/item/ItemWizardArmour$ArmourClass;)Z
  #454 = Utf8               func_77653_i
  #455 = Utf8               (Lnet/minecraft/item/ItemStack;)Ljava/lang/String;
  #456 = NameAndType        #454:#455     // func_77653_i:(Lnet/minecraft/item/ItemStack;)Ljava/lang/String;
  #457 = Methodref          #4.#456       // net/minecraft/item/Item.func_77653_i:(Lnet/minecraft/item/ItemStack;)Ljava/lang/String;
  #458 = Utf8               shouldCauseReequipAnimation
  #459 = Utf8               (Lnet/minecraft/item/ItemStack;Lnet/minecraft/item/ItemStack;Z)Z
  #460 = Utf8               func_190926_b
  #461 = NameAndType        #460:#125     // func_190926_b:()Z
  #462 = Methodref          #133.#461     // net/minecraft/item/ItemStack.func_190926_b:()Z
  #463 = NameAndType        #458:#459     // shouldCauseReequipAnimation:(Lnet/minecraft/item/ItemStack;Lnet/minecraft/item/ItemStack;Z)Z
  #464 = Methodref          #4.#463       // net/minecraft/item/Item.shouldCauseReequipAnimation:(Lnet/minecraft/item/ItemStack;Lnet/minecraft/item/ItemStack;Z)Z
  #465 = Utf8               slotChanged
  #466 = Utf8               cast
  #467 = Utf8               (Lnet/minecraft/item/ItemStack;Lelectroblob/wizardry/spell/Spell;Lnet/minecraft/entity/player/EntityPlayer;Lnet/minecraft/util/EnumHand;ILelectroblob/wizardry/util/SpellModifiers;)Z
  #468 = Utf8               net/minecraft/world/World
  #469 = Class              #468          // net/minecraft/world/World
  #470 = Utf8               field_72995_K
  #471 = NameAndType        #470:#196     // field_72995_K:Z
  #472 = Fieldref           #469.#471     // net/minecraft/world/World.field_72995_K:Z
  #473 = Utf8               electroblob/wizardry/spell/Spell
  #474 = Class              #473          // electroblob/wizardry/spell/Spell
  #475 = Utf8               isContinuous
  #476 = NameAndType        #475:#196     // isContinuous:Z
  #477 = Fieldref           #474.#476     // electroblob/wizardry/spell/Spell.isContinuous:Z
  #478 = Utf8               requiresPacket
  #479 = NameAndType        #478:#125     // requiresPacket:()Z
  #480 = Methodref          #474.#479     // electroblob/wizardry/spell/Spell.requiresPacket:()Z
  #481 = Utf8               (Lnet/minecraft/world/World;Lnet/minecraft/entity/player/EntityPlayer;Lnet/minecraft/util/EnumHand;ILelectroblob/wizardry/util/SpellModifiers;)Z
  #482 = NameAndType        #466:#481     // cast:(Lnet/minecraft/world/World;Lnet/minecraft/entity/player/EntityPlayer;Lnet/minecraft/util/EnumHand;ILelectroblob/wizardry/util/SpellModifiers;)Z
  #483 = Methodref          #474.#482     // electroblob/wizardry/spell/Spell.cast:(Lnet/minecraft/world/World;Lnet/minecraft/entity/player/EntityPlayer;Lnet/minecraft/util/EnumHand;ILelectroblob/wizardry/util/SpellModifiers;)Z
  #484 = Utf8               net/minecraftforge/common/MinecraftForge
  #485 = Class              #484          // net/minecraftforge/common/MinecraftForge
  #486 = Utf8               EVENT_BUS
  #487 = Utf8               Lnet/minecraftforge/fml/common/eventhandler/EventBus;
  #488 = NameAndType        #486:#487     // EVENT_BUS:Lnet/minecraftforge/fml/common/eventhandler/EventBus;
  #489 = Fieldref           #485.#488     // net/minecraftforge/common/MinecraftForge.EVENT_BUS:Lnet/minecraftforge/fml/common/eventhandler/EventBus;
  #490 = Utf8               OTHER
  #491 = Utf8               Lelectroblob/wizardry/event/SpellCastEvent$Source;
  #492 = NameAndType        #490:#491     // OTHER:Lelectroblob/wizardry/event/SpellCastEvent$Source;
  #493 = Fieldref           #37.#492      // electroblob/wizardry/event/SpellCastEvent$Source.OTHER:Lelectroblob/wizardry/event/SpellCastEvent$Source;
  #494 = Utf8               (Lelectroblob/wizardry/event/SpellCastEvent$Source;Lelectroblob/wizardry/spell/Spell;Lnet/minecraft/entity/EntityLivingBase;Lelectroblob/wizardry/util/SpellModifiers;)V
  #495 = NameAndType        #43:#494      // "<init>":(Lelectroblob/wizardry/event/SpellCastEvent$Source;Lelectroblob/wizardry/spell/Spell;Lnet/minecraft/entity/EntityLivingBase;Lelectroblob/wizardry/util/SpellModifiers;)V
  #496 = Methodref          #17.#495      // electroblob/wizardry/event/SpellCastEvent$Post."<init>":(Lelectroblob/wizardry/event/SpellCastEvent$Source;Lelectroblob/wizardry/spell/Spell;Lnet/minecraft/entity/EntityLivingBase;Lelectroblob/wizardry/util/SpellModifiers;)V
  #497 = Utf8               net/minecraftforge/fml/common/eventhandler/EventBus
  #498 = Class              #497          // net/minecraftforge/fml/common/eventhandler/EventBus
  #499 = Utf8               post
  #500 = Utf8               (Lnet/minecraftforge/fml/common/eventhandler/Event;)Z
  #501 = NameAndType        #499:#500     // post:(Lnet/minecraftforge/fml/common/eventhandler/Event;)Z
  #502 = Methodref          #498.#501     // net/minecraftforge/fml/common/eventhandler/EventBus.post:(Lnet/minecraftforge/fml/common/eventhandler/Event;)Z
  #503 = Utf8               func_145782_y
  #504 = NameAndType        #503:#163     // func_145782_y:()I
  #505 = Methodref          #359.#504     // net/minecraft/entity/player/EntityPlayer.func_145782_y:()I
  #506 = Utf8               (ILnet/minecraft/util/EnumHand;Lelectroblob/wizardry/spell/Spell;Lelectroblob/wizardry/util/SpellModifiers;)V
  #507 = NameAndType        #43:#506      // "<init>":(ILnet/minecraft/util/EnumHand;Lelectroblob/wizardry/spell/Spell;Lelectroblob/wizardry/util/SpellModifiers;)V
  #508 = Methodref          #22.#507      // electroblob/wizardry/packet/PacketCastSpell$Message."<init>":(ILnet/minecraft/util/EnumHand;Lelectroblob/wizardry/spell/Spell;Lelectroblob/wizardry/util/SpellModifiers;)V
  #509 = Utf8               electroblob/wizardry/packet/WizardryPacketHandler
  #510 = Class              #509          // electroblob/wizardry/packet/WizardryPacketHandler
  #511 = Utf8               net
  #512 = Utf8               Lnet/minecraftforge/fml/common/network/simpleimpl/SimpleNetworkWrapper;
  #513 = NameAndType        #511:#512     // net:Lnet/minecraftforge/fml/common/network/simpleimpl/SimpleNetworkWrapper;
  #514 = Fieldref           #510.#513     // electroblob/wizardry/packet/WizardryPacketHandler.net:Lnet/minecraftforge/fml/common/network/simpleimpl/SimpleNetworkWrapper;
  #515 = Utf8               field_73011_w
  #516 = Utf8               Lnet/minecraft/world/WorldProvider;
  #517 = NameAndType        #515:#516     // field_73011_w:Lnet/minecraft/world/WorldProvider;
  #518 = Fieldref           #469.#517     // net/minecraft/world/World.field_73011_w:Lnet/minecraft/world/WorldProvider;
  #519 = Utf8               net/minecraft/world/WorldProvider
  #520 = Class              #519          // net/minecraft/world/WorldProvider
  #521 = Utf8               getDimension
  #522 = NameAndType        #521:#163     // getDimension:()I
  #523 = Methodref          #520.#522     // net/minecraft/world/WorldProvider.getDimension:()I
  #524 = Utf8               net/minecraftforge/fml/common/network/simpleimpl/SimpleNetworkWrapper
  #525 = Class              #524          // net/minecraftforge/fml/common/network/simpleimpl/SimpleNetworkWrapper
  #526 = Utf8               sendToDimension
  #527 = Utf8               (Lnet/minecraftforge/fml/common/network/simpleimpl/IMessage;I)V
  #528 = NameAndType        #526:#527     // sendToDimension:(Lnet/minecraftforge/fml/common/network/simpleimpl/IMessage;I)V
  #529 = Methodref          #525.#528     // net/minecraftforge/fml/common/network/simpleimpl/SimpleNetworkWrapper.sendToDimension:(Lnet/minecraftforge/fml/common/network/simpleimpl/IMessage;I)V
  #530 = Utf8               msg
  #531 = Utf8               Lnet/minecraftforge/fml/common/network/simpleimpl/IMessage;
  #532 = Utf8               spell
  #533 = Utf8               Lelectroblob/wizardry/spell/Spell;
  #534 = Utf8               caster
  #535 = Utf8               castingTick
  #536 = Utf8               modifiers
  #537 = Utf8               Lelectroblob/wizardry/util/SpellModifiers;
  #538 = Utf8               world
  #539 = Utf8               getCurrentSpell
  #540 = Utf8               (Lnet/minecraft/item/ItemStack;)Lelectroblob/wizardry/spell/Spell;
  #541 = Utf8               Ljavax/annotation/Nonnull;
  #542 = Utf8               electroblob/wizardry/registry/Spells
  #543 = Class              #542          // electroblob/wizardry/registry/Spells
  #544 = NameAndType        #258:#533     // shield:Lelectroblob/wizardry/spell/Spell;
  #545 = Fieldref           #543.#544     // electroblob/wizardry/registry/Spells.shield:Lelectroblob/wizardry/spell/Spell;
  #546 = Utf8               showSpellHUD
  #547 = Utf8               (Lnet/minecraft/entity/player/EntityPlayer;Lnet/minecraft/item/ItemStack;)Z
  #548 = Utf8               canCast
  #549 = Utf8               func_111205_h
  #550 = Utf8               (Lnet/minecraft/inventory/EntityEquipmentSlot;)Lcom/google/common/collect/Multimap;
  #551 = Utf8               (Lnet/minecraft/inventory/EntityEquipmentSlot;)Lcom/google/common/collect/Multimap<Ljava/lang/String;Lnet/minecraft/entity/ai/attributes/AttributeModifier;>;
  #552 = NameAndType        #549:#550     // func_111205_h:(Lnet/minecraft/inventory/EntityEquipmentSlot;)Lcom/google/common/collect/Multimap;
  #553 = Methodref          #4.#552       // net/minecraft/item/Item.func_111205_h:(Lnet/minecraft/inventory/EntityEquipmentSlot;)Lcom/google/common/collect/Multimap;
  #554 = Utf8               net/minecraft/inventory/EntityEquipmentSlot
  #555 = Class              #554          // net/minecraft/inventory/EntityEquipmentSlot
  #556 = Utf8               OFFHAND
  #557 = Utf8               Lnet/minecraft/inventory/EntityEquipmentSlot;
  #558 = NameAndType        #556:#557     // OFFHAND:Lnet/minecraft/inventory/EntityEquipmentSlot;
  #559 = Fieldref           #555.#558     // net/minecraft/inventory/EntityEquipmentSlot.OFFHAND:Lnet/minecraft/inventory/EntityEquipmentSlot;
  #560 = Utf8               net/minecraft/entity/SharedMonsterAttributes
  #561 = Class              #560          // net/minecraft/entity/SharedMonsterAttributes
  #562 = Utf8               field_188791_g
  #563 = Utf8               Lnet/minecraft/entity/ai/attributes/IAttribute;
  #564 = NameAndType        #562:#563     // field_188791_g:Lnet/minecraft/entity/ai/attributes/IAttribute;
  #565 = Fieldref           #561.#564     // net/minecraft/entity/SharedMonsterAttributes.field_188791_g:Lnet/minecraft/entity/ai/attributes/IAttribute;
  #566 = Utf8               net/minecraft/entity/ai/attributes/IAttribute
  #567 = Class              #566          // net/minecraft/entity/ai/attributes/IAttribute
  #568 = Utf8               func_111108_a
  #569 = NameAndType        #568:#301     // func_111108_a:()Ljava/lang/String;
  #570 = InterfaceMethodref #567.#569     // net/minecraft/entity/ai/attributes/IAttribute.func_111108_a:()Ljava/lang/String;
  #571 = Utf8               net/minecraft/entity/ai/attributes/AttributeModifier
  #572 = Class              #571          // net/minecraft/entity/ai/attributes/AttributeModifier
  #573 = NameAndType        #39:#40       // SHIELD_ARMOR_BONUS:Ljava/util/UUID;
  #574 = Fieldref           #2.#573       // com/windanesz/ancientspellcraft/item/ItemBattlemageShield.SHIELD_ARMOR_BONUS:Ljava/util/UUID;
  #575 = Utf8               Armor modifier
  #576 = String             #575          // Armor modifier
  #577 = Utf8               runic_shield_armor
  #578 = Utf8               F
  #579 = NameAndType        #577:#578     // runic_shield_armor:F
  #580 = Fieldref           #27.#579      // com/windanesz/ancientspellcraft/Settings$GeneralSettings.runic_shield_armor:F
  #581 = Utf8               (Ljava/util/UUID;Ljava/lang/String;DI)V
  #582 = NameAndType        #43:#581      // "<init>":(Ljava/util/UUID;Ljava/lang/String;DI)V
  #583 = Methodref          #572.#582     // net/minecraft/entity/ai/attributes/AttributeModifier."<init>":(Ljava/util/UUID;Ljava/lang/String;DI)V
  #584 = Utf8               com/google/common/collect/Multimap
  #585 = Class              #584          // com/google/common/collect/Multimap
  #586 = Utf8               put
  #587 = Utf8               (Ljava/lang/Object;Ljava/lang/Object;)Z
  #588 = NameAndType        #586:#587     // put:(Ljava/lang/Object;Ljava/lang/Object;)Z
  #589 = InterfaceMethodref #585.#588     // com/google/common/collect/Multimap.put:(Ljava/lang/Object;Ljava/lang/Object;)Z
  #590 = Utf8               field_189429_h
  #591 = NameAndType        #590:#563     // field_189429_h:Lnet/minecraft/entity/ai/attributes/IAttribute;
  #592 = Fieldref           #561.#591     // net/minecraft/entity/SharedMonsterAttributes.field_189429_h:Lnet/minecraft/entity/ai/attributes/IAttribute;
  #593 = NameAndType        #42:#40       // SHIELD_TOUGHNESS_BONUS:Ljava/util/UUID;
  #594 = Fieldref           #2.#593       // com/windanesz/ancientspellcraft/item/ItemBattlemageShield.SHIELD_TOUGHNESS_BONUS:Ljava/util/UUID;
  #595 = Utf8               Armor toughness
  #596 = String             #595          // Armor toughness
  #597 = Utf8               runic_shield_armor_toughness
  #598 = NameAndType        #597:#578     // runic_shield_armor_toughness:F
  #599 = Fieldref           #27.#598      // com/windanesz/ancientspellcraft/Settings$GeneralSettings.runic_shield_armor_toughness:F
  #600 = Utf8               slot
  #601 = Utf8               multimap
  #602 = Utf8               Lcom/google/common/collect/Multimap<Ljava/lang/String;Lnet/minecraft/entity/ai/attributes/AttributeModifier;>;
  #603 = Utf8               Lcom/google/common/collect/Multimap;
  #604 = Utf8               func_77663_a
  #605 = Utf8               (Lnet/minecraft/item/ItemStack;Lnet/minecraft/world/World;Lnet/minecraft/entity/Entity;IZ)V
  #606 = NameAndType        #604:#605     // func_77663_a:(Lnet/minecraft/item/ItemStack;Lnet/minecraft/world/World;Lnet/minecraft/entity/Entity;IZ)V
  #607 = Methodref          #4.#606       // net/minecraft/item/Item.func_77663_a:(Lnet/minecraft/item/ItemStack;Lnet/minecraft/world/World;Lnet/minecraft/entity/Entity;IZ)V
  #608 = Utf8               func_184592_cb
  #609 = NameAndType        #608:#129     // func_184592_cb:()Lnet/minecraft/item/ItemStack;
  #610 = Methodref          #359.#609     // net/minecraft/entity/player/EntityPlayer.func_184592_cb:()Lnet/minecraft/item/ItemStack;
  #611 = Utf8               func_77942_o
  #612 = NameAndType        #611:#125     // func_77942_o:()Z
  #613 = Methodref          #133.#612     // net/minecraft/item/ItemStack.func_77942_o:()Z
  #614 = Utf8               func_77978_p
  #615 = Utf8               ()Lnet/minecraft/nbt/NBTTagCompound;
  #616 = NameAndType        #614:#615     // func_77978_p:()Lnet/minecraft/nbt/NBTTagCompound;
  #617 = Methodref          #133.#616     // net/minecraft/item/ItemStack.func_77978_p:()Lnet/minecraft/nbt/NBTTagCompound;
  #618 = Utf8               Items
  #619 = String             #618          // Items
  #620 = Utf8               net/minecraft/nbt/NBTTagCompound
  #621 = Class              #620          // net/minecraft/nbt/NBTTagCompound
  #622 = Utf8               func_74764_b
  #623 = Utf8               (Ljava/lang/String;)Z
  #624 = NameAndType        #622:#623     // func_74764_b:(Ljava/lang/String;)Z
  #625 = Methodref          #621.#624     // net/minecraft/nbt/NBTTagCompound.func_74764_b:(Ljava/lang/String;)Z
  #626 = Utf8               func_150295_c
  #627 = Utf8               (Ljava/lang/String;I)Lnet/minecraft/nbt/NBTTagList;
  #628 = NameAndType        #626:#627     // func_150295_c:(Ljava/lang/String;I)Lnet/minecraft/nbt/NBTTagList;
  #629 = Methodref          #621.#628     // net/minecraft/nbt/NBTTagCompound.func_150295_c:(Ljava/lang/String;I)Lnet/minecraft/nbt/NBTTagList;
  #630 = Utf8               net/minecraft/nbt/NBTTagList
  #631 = Class              #630          // net/minecraft/nbt/NBTTagList
  #632 = Utf8               func_74745_c
  #633 = NameAndType        #632:#163     // func_74745_c:()I
  #634 = Methodref          #631.#633     // net/minecraft/nbt/NBTTagList.func_74745_c:()I
  #635 = Utf8               func_150305_b
  #636 = Utf8               (I)Lnet/minecraft/nbt/NBTTagCompound;
  #637 = NameAndType        #635:#636     // func_150305_b:(I)Lnet/minecraft/nbt/NBTTagCompound;
  #638 = Methodref          #631.#637     // net/minecraft/nbt/NBTTagList.func_150305_b:(I)Lnet/minecraft/nbt/NBTTagCompound;
  #639 = Utf8               (Lnet/minecraft/nbt/NBTTagCompound;)V
  #640 = NameAndType        #43:#639      // "<init>":(Lnet/minecraft/nbt/NBTTagCompound;)V
  #641 = Methodref          #133.#640     // net/minecraft/item/ItemStack."<init>":(Lnet/minecraft/nbt/NBTTagCompound;)V
  #642 = Utf8               tickArtefact
  #643 = Utf8               (Lnet/minecraft/item/ItemStack;Lnet/minecraft/entity/player/EntityPlayer;)V
  #644 = NameAndType        #642:#643     // tickArtefact:(Lnet/minecraft/item/ItemStack;Lnet/minecraft/entity/player/EntityPlayer;)V
  #645 = Methodref          #2.#644       // com/windanesz/ancientspellcraft/item/ItemBattlemageShield.tickArtefact:(Lnet/minecraft/item/ItemStack;Lnet/minecraft/entity/player/EntityPlayer;)V
  #646 = Utf8               func_82737_E
  #647 = Utf8               ()J
  #648 = NameAndType        #646:#647     // func_82737_E:()J
  #649 = Methodref          #469.#648     // net/minecraft/world/World.func_82737_E:()J
  #650 = Long               50l
  #652 = Utf8               func_184811_cZ
  #653 = Utf8               ()Lnet/minecraft/util/CooldownTracker;
  #654 = NameAndType        #652:#653     // func_184811_cZ:()Lnet/minecraft/util/CooldownTracker;
  #655 = Methodref          #359.#654     // net/minecraft/entity/player/EntityPlayer.func_184811_cZ:()Lnet/minecraft/util/CooldownTracker;
  #656 = Utf8               net/minecraft/util/CooldownTracker
  #657 = Class              #656          // net/minecraft/util/CooldownTracker
  #658 = Utf8               func_185141_a
  #659 = NameAndType        #658:#219     // func_185141_a:(Lnet/minecraft/item/Item;)Z
  #660 = Methodref          #657.#659     // net/minecraft/util/CooldownTracker.func_185141_a:(Lnet/minecraft/item/Item;)Z
  #661 = Utf8               charm_glyph_shield_disable
  #662 = NameAndType        #661:#204     // charm_glyph_shield_disable:Lnet/minecraft/item/Item;
  #663 = Fieldref           #229.#662     // com/windanesz/ancientspellcraft/registry/ASItems.charm_glyph_shield_disable:Lnet/minecraft/item/Item;
  #664 = Utf8               electroblob/wizardry/item/ItemArtefact
  #665 = Class              #664          // electroblob/wizardry/item/ItemArtefact
  #666 = Utf8               isArtefactActive
  #667 = Utf8               (Lnet/minecraft/entity/player/EntityPlayer;Lnet/minecraft/item/Item;)Z
  #668 = NameAndType        #666:#667     // isArtefactActive:(Lnet/minecraft/entity/player/EntityPlayer;Lnet/minecraft/item/Item;)Z
  #669 = Methodref          #665.#668     // electroblob/wizardry/item/ItemArtefact.isArtefactActive:(Lnet/minecraft/entity/player/EntityPlayer;Lnet/minecraft/item/Item;)Z
  #670 = Utf8               func_185142_b
  #671 = NameAndType        #670:#111     // func_185142_b:(Lnet/minecraft/item/Item;)V
  #672 = Methodref          #657.#671     // net/minecraft/util/CooldownTracker.func_185142_b:(Lnet/minecraft/item/Item;)V
  #673 = Utf8               i
  #674 = Utf8               nbt
  #675 = Utf8               Lnet/minecraft/nbt/NBTTagCompound;
  #676 = Utf8               entity
  #677 = Utf8               Lnet/minecraft/entity/Entity;
  #678 = Utf8               itemSlot
  #679 = Utf8               isSelected
  #680 = Utf8               getArtefacts
  #681 = Utf8               (Lnet/minecraft/item/ItemStack;)Ljava/util/List;
  #682 = Utf8               (Lnet/minecraft/item/ItemStack;)Ljava/util/List<Lnet/minecraft/item/ItemStack;>;
  #683 = Utf8               java/util/ArrayList
  #684 = Class              #683          // java/util/ArrayList
  #685 = Methodref          #684.#45      // java/util/ArrayList."<init>":()V
  #686 = Utf8               artefacts
  #687 = Utf8               Ljava/util/List<Lnet/minecraft/item/ItemStack;>;
  #688 = Utf8               com/windanesz/ancientspellcraft/item/ITickableArtefact
  #689 = Class              #688          // com/windanesz/ancientspellcraft/item/ITickableArtefact
  #690 = Utf8               onWornTick
  #691 = Utf8               (Lnet/minecraft/item/ItemStack;Lnet/minecraft/entity/EntityLivingBase;)V
  #692 = NameAndType        #690:#691     // onWornTick:(Lnet/minecraft/item/ItemStack;Lnet/minecraft/entity/EntityLivingBase;)V
  #693 = InterfaceMethodref #689.#692     // com/windanesz/ancientspellcraft/item/ITickableArtefact.onWornTick:(Lnet/minecraft/item/ItemStack;Lnet/minecraft/entity/EntityLivingBase;)V
  #694 = Utf8               func_77616_k
  #695 = Utf8               func_77619_b
  #696 = Utf8               isBookEnchantable
  #697 = Utf8               book
  #698 = Utf8               func_82789_a
  #699 = Utf8               toRepair
  #700 = Utf8               repair
  #701 = Utf8               isShield
  #702 = Utf8               (Lnet/minecraft/item/ItemStack;Lnet/minecraft/entity/EntityLivingBase;)Z
  #703 = Utf8               getSlotCount
  #704 = Utf8               hasGUI
  #705 = Utf8               getRowCount
  #706 = Utf8               getColumnCount
  #707 = Utf8               isItemValid
  #708 = Utf8               item
  #709 = Utf8               <clinit>
  #710 = Utf8               2b5b1f50-b6b5-473a-a402-e45a24d83c13
  #711 = String             #710          // 2b5b1f50-b6b5-473a-a402-e45a24d83c13
  #712 = Utf8               java/util/UUID
  #713 = Class              #712          // java/util/UUID
  #714 = Utf8               fromString
  #715 = Utf8               (Ljava/lang/String;)Ljava/util/UUID;
  #716 = NameAndType        #714:#715     // fromString:(Ljava/lang/String;)Ljava/util/UUID;
  #717 = Methodref          #713.#716     // java/util/UUID.fromString:(Ljava/lang/String;)Ljava/util/UUID;
  #718 = Utf8               3c1acb30-dafb-4c27-a142-680f12ed9c36
  #719 = String             #718          // 3c1acb30-dafb-4c27-a142-680f12ed9c36
  #720 = NameAndType        #41:#40       // SHIELD_ARMOR_PERCENT_BONUS:Ljava/util/UUID;
  #721 = Fieldref           #2.#720       // com/windanesz/ancientspellcraft/item/ItemBattlemageShield.SHIELD_ARMOR_PERCENT_BONUS:Ljava/util/UUID;
  #722 = Utf8               84d9a7e1-5346-4073-98e9-0e04d6d28da5
  #723 = String             #722          // 84d9a7e1-5346-4073-98e9-0e04d6d28da5
  #724 = Utf8               Code
  #725 = Utf8               LineNumberTable
  #726 = Utf8               LocalVariableTable
  #727 = Utf8               StackMapTable
  #728 = Utf8               RuntimeVisibleParameterAnnotations
  #729 = Utf8               LocalVariableTypeTable
  #730 = Utf8               Signature
  #731 = Utf8               RuntimeVisibleAnnotations
  #732 = Utf8               InnerClasses
  #733 = Utf8               SourceFile
{
  public com.windanesz.ancientspellcraft.item.ItemBattlemageShield();
    descriptor: ()V
    flags: ACC_PUBLIC
    Code:
      stack=5, locals=1, args_size=1
         0: aload_0
         1: invokespecial #46                 // Method net/minecraft/item/Item."<init>":()V
         4: aload_0
         5: invokevirtual #50                 // Method func_77664_n:()Lnet/minecraft/item/Item;
         8: pop
         9: aload_0
        10: iconst_1
        11: putfield      #54                 // Field field_77777_bU:I
        14: aload_0
        15: getstatic     #60                 // Field com/windanesz/ancientspellcraft/registry/ASTabs.ANCIENTSPELLCRAFT_GEAR:Lnet/minecraft/creativetab/CreativeTabs;
        18: invokevirtual #64                 // Method func_77637_a:(Lnet/minecraft/creativetab/CreativeTabs;)Lnet/minecraft/item/Item;
        21: pop
        22: aload_0
        23: getstatic     #68                 // Field com/windanesz/ancientspellcraft/Settings.generalSettings:Lcom/windanesz/ancientspellcraft/Settings$GeneralSettings;
        26: getfield      #71                 // Field com/windanesz/ancientspellcraft/Settings$GeneralSettings.runic_shield_durability:I
        29: invokevirtual #75                 // Method func_77656_e:(I)Lnet/minecraft/item/Item;
        32: pop
        33: aload_0
        34: new           #77                 // class net/minecraft/util/ResourceLocation
        37: dup
        38: ldc           #79                 // String blocking
        40: invokespecial #82                 // Method net/minecraft/util/ResourceLocation."<init>":(Ljava/lang/String;)V
        43: new           #15                 // class com/windanesz/ancientspellcraft/item/ItemBattlemageShield$1
        46: dup
        47: aload_0
        48: invokespecial #85                 // Method com/windanesz/ancientspellcraft/item/ItemBattlemageShield$1."<init>":(Lcom/windanesz/ancientspellcraft/item/ItemBattlemageShield;)V
        51: invokevirtual #89                 // Method func_185043_a:(Lnet/minecraft/util/ResourceLocation;Lnet/minecraft/item/IItemPropertyGetter;)V
        54: getstatic     #95                 // Field net/minecraft/block/BlockDispenser.field_149943_a:Lnet/minecraft/util/registry/RegistryDefaulted;
        57: aload_0
        58: getstatic     #101                // Field net/minecraft/item/ItemArmor.field_96605_cw:Lnet/minecraft/dispenser/IBehaviorDispenseItem;
        61: invokevirtual #107                // Method net/minecraft/util/registry/RegistryDefaulted.func_82595_a:(Ljava/lang/Object;Ljava/lang/Object;)V
        64: aload_0
        65: invokestatic  #113                // Method electroblob/wizardry/registry/WizardryRecipes.addToManaFlaskCharging:(Lnet/minecraft/item/Item;)V
        68: return
      LineNumberTable:
        line 65: 0
        line 66: 4
        line 67: 9
        line 68: 14
        line 69: 22
        line 70: 33
        line 76: 54
        line 77: 64
        line 78: 68
      LocalVariableTable:
        Start  Length  Slot  Name   Signature
            0      69     0  this   Lcom/windanesz/ancientspellcraft/item/ItemBattlemageShield;

  public int getSpellSlotCount(net.minecraft.item.ItemStack);
    descriptor: (Lnet/minecraft/item/ItemStack;)I
    flags: ACC_PUBLIC
    Code:
      stack=1, locals=2, args_size=2
         0: iconst_0
         1: ireturn
      LineNumberTable:
        line 82: 0
      LocalVariableTable:
        Start  Length  Slot  Name   Signature
            0       2     0  this   Lcom/windanesz/ancientspellcraft/item/ItemBattlemageShield;
            0       2     1 stack   Lnet/minecraft/item/ItemStack;

  public boolean onApplyButtonPressed(net.minecraft.entity.player.EntityPlayer, net.minecraft.inventory.Slot, net.minecraft.inventory.Slot, net.minecraft.inventory.Slot, net.minecraft.inventory.Slot[]);
    descriptor: (Lnet/minecraft/entity/player/EntityPlayer;Lnet/minecraft/inventory/Slot;Lnet/minecraft/inventory/Slot;Lnet/minecraft/inventory/Slot;[Lnet/minecraft/inventory/Slot;)Z
    flags: ACC_PUBLIC
    Code:
      stack=5, locals=8, args_size=6
         0: iconst_0
         1: istore        6
         3: aload         4
         5: invokevirtual #127                // Method net/minecraft/inventory/Slot.func_75216_d:()Z
         8: ifeq          57
        11: aload_2
        12: invokevirtual #131                // Method net/minecraft/inventory/Slot.func_75211_c:()Lnet/minecraft/item/ItemStack;
        15: invokevirtual #136                // Method net/minecraft/item/ItemStack.func_77946_l:()Lnet/minecraft/item/ItemStack;
        18: astore        7
        20: aload_2
        21: aload_0
        22: aload_1
        23: aload_2
        24: invokevirtual #131                // Method net/minecraft/inventory/Slot.func_75211_c:()Lnet/minecraft/item/ItemStack;
        27: aload         4
        29: invokevirtual #131                // Method net/minecraft/inventory/Slot.func_75211_c:()Lnet/minecraft/item/ItemStack;
        32: invokevirtual #140                // Method applyUpgrade:(Lnet/minecraft/entity/player/EntityPlayer;Lnet/minecraft/item/ItemStack;Lnet/minecraft/item/ItemStack;)Lnet/minecraft/item/ItemStack;
        35: invokevirtual #144                // Method net/minecraft/inventory/Slot.func_75215_d:(Lnet/minecraft/item/ItemStack;)V
        38: aload_2
        39: invokevirtual #131                // Method net/minecraft/inventory/Slot.func_75211_c:()Lnet/minecraft/item/ItemStack;
        42: aload         7
        44: invokestatic  #148                // Method net/minecraft/item/ItemStack.func_77989_b:(Lnet/minecraft/item/ItemStack;Lnet/minecraft/item/ItemStack;)Z
        47: ifne          54
        50: iconst_1
        51: goto          55
        54: iconst_0
        55: istore        6
        57: aload_3
        58: invokevirtual #131                // Method net/minecraft/inventory/Slot.func_75211_c:()Lnet/minecraft/item/ItemStack;
        61: getstatic     #151                // Field net/minecraft/item/ItemStack.field_190927_a:Lnet/minecraft/item/ItemStack;
        64: if_acmpeq     180
        67: aload_0
        68: aload_2
        69: invokevirtual #131                // Method net/minecraft/inventory/Slot.func_75211_c:()Lnet/minecraft/item/ItemStack;
        72: invokevirtual #155                // Method isManaFull:(Lnet/minecraft/item/ItemStack;)Z
        75: ifne          180
        78: aload_0
        79: aload_2
        80: invokevirtual #131                // Method net/minecraft/inventory/Slot.func_75211_c:()Lnet/minecraft/item/ItemStack;
        83: invokevirtual #158                // Method getManaCapacity:(Lnet/minecraft/item/ItemStack;)I
        86: aload_0
        87: aload_2
        88: invokevirtual #131                // Method net/minecraft/inventory/Slot.func_75211_c:()Lnet/minecraft/item/ItemStack;
        91: invokevirtual #161                // Method getMana:(Lnet/minecraft/item/ItemStack;)I
        94: isub
        95: istore        7
        97: aload_3
        98: invokevirtual #131                // Method net/minecraft/inventory/Slot.func_75211_c:()Lnet/minecraft/item/ItemStack;
       101: invokevirtual #165                // Method net/minecraft/item/ItemStack.func_190916_E:()I
       104: bipush        100
       106: imul
       107: iload         7
       109: if_icmpge     145
       112: aload_0
       113: aload_2
       114: invokevirtual #131                // Method net/minecraft/inventory/Slot.func_75211_c:()Lnet/minecraft/item/ItemStack;
       117: aload_3
       118: invokevirtual #131                // Method net/minecraft/inventory/Slot.func_75211_c:()Lnet/minecraft/item/ItemStack;
       121: invokevirtual #165                // Method net/minecraft/item/ItemStack.func_190916_E:()I
       124: bipush        100
       126: imul
       127: invokevirtual #169                // Method rechargeMana:(Lnet/minecraft/item/ItemStack;I)V
       130: aload_3
       131: aload_3
       132: invokevirtual #131                // Method net/minecraft/inventory/Slot.func_75211_c:()Lnet/minecraft/item/ItemStack;
       135: invokevirtual #165                // Method net/minecraft/item/ItemStack.func_190916_E:()I
       138: invokevirtual #173                // Method net/minecraft/inventory/Slot.func_75209_a:(I)Lnet/minecraft/item/ItemStack;
       141: pop
       142: goto          177
       145: aload_0
       146: aload_2
       147: invokevirtual #131                // Method net/minecraft/inventory/Slot.func_75211_c:()Lnet/minecraft/item/ItemStack;
       150: aload_0
       151: aload_2
       152: invokevirtual #131                // Method net/minecraft/inventory/Slot.func_75211_c:()Lnet/minecraft/item/ItemStack;
       155: invokevirtual #158                // Method getManaCapacity:(Lnet/minecraft/item/ItemStack;)I
       158: invokevirtual #176                // Method setMana:(Lnet/minecraft/item/ItemStack;I)V
       161: aload_3
       162: iload         7
       164: i2d
       165: ldc2_w        #177                // double 100.0d
       168: ddiv
       169: invokestatic  #184                // Method java/lang/Math.ceil:(D)D
       172: d2i
       173: invokevirtual #173                // Method net/minecraft/inventory/Slot.func_75209_a:(I)Lnet/minecraft/item/ItemStack;
       176: pop
       177: iconst_1
       178: istore        6
       180: iload         6
       182: ireturn
      StackMapTable: number_of_entries = 6
        frame_type = 253 /* append */
          offset_delta = 54
          locals = [ int, class net/minecraft/item/ItemStack ]
        frame_type = 64 /* same_locals_1_stack_item */
          stack = [ int ]
        frame_type = 250 /* chop */
          offset_delta = 1
        frame_type = 252 /* append */
          offset_delta = 87
          locals = [ int ]
        frame_type = 31 /* same */
        frame_type = 250 /* chop */
          offset_delta = 2
      LineNumberTable:
        line 87: 0
        line 89: 3
        line 90: 11
        line 91: 20
        line 92: 38
        line 97: 57
        line 99: 78
        line 101: 97
        line 103: 112
        line 104: 130
        line 108: 145
        line 109: 161
        line 112: 177
        line 115: 180
      LocalVariableTable:
        Start  Length  Slot  Name   Signature
           20      37     7 original   Lnet/minecraft/item/ItemStack;
           97      83     7 chargeDepleted   I
            0     183     0  this   Lcom/windanesz/ancientspellcraft/item/ItemBattlemageShield;
            0     183     1 player   Lnet/minecraft/entity/player/EntityPlayer;
            0     183     2 centre   Lnet/minecraft/inventory/Slot;
            0     183     3 crystals   Lnet/minecraft/inventory/Slot;
            0     183     4 upgrade   Lnet/minecraft/inventory/Slot;
            0     183     5 spellBooks   [Lnet/minecraft/inventory/Slot;
            3     180     6 changed   Z

  public int getMaxDamage(net.minecraft.item.ItemStack);
    descriptor: (Lnet/minecraft/item/ItemStack;)I
    flags: ACC_PUBLIC
    Code:
      stack=5, locals=2, args_size=2
         0: aload_0
         1: aload_1
         2: invokespecial #199                // Method net/minecraft/item/Item.getMaxDamage:(Lnet/minecraft/item/ItemStack;)I
         5: i2f
         6: fconst_1
         7: ldc           #200                // float 0.15f
         9: aload_1
        10: getstatic     #206                // Field electroblob/wizardry/registry/WizardryItems.storage_upgrade:Lnet/minecraft/item/Item;
        13: invokestatic  #212                // Method electroblob/wizardry/util/WandHelper.getUpgradeLevel:(Lnet/minecraft/item/ItemStack;Lnet/minecraft/item/Item;)I
        16: i2f
        17: fmul
        18: fadd
        19: fmul
        20: ldc           #213                // float 0.5f
        22: fadd
        23: f2i
        24: ireturn
      LineNumberTable:
        line 119: 0
      LocalVariableTable:
        Start  Length  Slot  Name   Signature
            0      25     0  this   Lcom/windanesz/ancientspellcraft/item/ItemBattlemageShield;
            0      25     1 stack   Lnet/minecraft/item/ItemStack;

  public net.minecraft.item.ItemStack applyUpgrade(net.minecraft.entity.player.EntityPlayer, net.minecraft.item.ItemStack, net.minecraft.item.ItemStack);
    descriptor: (Lnet/minecraft/entity/player/EntityPlayer;Lnet/minecraft/item/ItemStack;Lnet/minecraft/item/ItemStack;)Lnet/minecraft/item/ItemStack;
    flags: ACC_PUBLIC
    Code:
      stack=3, locals=7, args_size=4
         0: aload_3
         1: invokevirtual #217                // Method net/minecraft/item/ItemStack.func_77973_b:()Lnet/minecraft/item/Item;
         4: invokestatic  #221                // Method electroblob/wizardry/util/WandHelper.isWandUpgrade:(Lnet/minecraft/item/Item;)Z
         7: ifeq          115
        10: aload_3
        11: invokevirtual #217                // Method net/minecraft/item/ItemStack.func_77973_b:()Lnet/minecraft/item/Item;
        14: astore        4
        16: aload         4
        18: getstatic     #206                // Field electroblob/wizardry/registry/WizardryItems.storage_upgrade:Lnet/minecraft/item/Item;
        21: if_acmpeq     48
        24: aload         4
        26: getstatic     #224                // Field electroblob/wizardry/registry/WizardryItems.siphon_upgrade:Lnet/minecraft/item/Item;
        29: if_acmpeq     48
        32: aload         4
        34: getstatic     #227                // Field electroblob/wizardry/registry/WizardryItems.condenser_upgrade:Lnet/minecraft/item/Item;
        37: if_acmpeq     48
        40: aload         4
        42: getstatic     #232                // Field com/windanesz/ancientspellcraft/registry/ASItems.soulbound_upgrade:Lnet/minecraft/item/Item;
        45: if_acmpne     115
        48: bipush        9
        50: istore        5
        52: aload_2
        53: invokestatic  #235                // Method electroblob/wizardry/util/WandHelper.getTotalUpgrades:(Lnet/minecraft/item/ItemStack;)I
        56: iload         5
        58: if_icmpge     115
        61: aload_2
        62: aload         4
        64: invokestatic  #212                // Method electroblob/wizardry/util/WandHelper.getUpgradeLevel:(Lnet/minecraft/item/ItemStack;Lnet/minecraft/item/Item;)I
        67: iconst_3
        68: if_icmpge     115
        71: aload_0
        72: aload_2
        73: invokevirtual #161                // Method getMana:(Lnet/minecraft/item/ItemStack;)I
        76: istore        6
        78: aload_2
        79: aload         4
        81: invokestatic  #238                // Method electroblob/wizardry/util/WandHelper.applyUpgrade:(Lnet/minecraft/item/ItemStack;Lnet/minecraft/item/Item;)V
        84: aload         4
        86: getstatic     #206                // Field electroblob/wizardry/registry/WizardryItems.storage_upgrade:Lnet/minecraft/item/Item;
        89: if_acmpne     99
        92: aload_0
        93: aload_2
        94: iload         6
        96: invokevirtual #176                // Method setMana:(Lnet/minecraft/item/ItemStack;I)V
        99: aload_3
       100: iconst_1
       101: invokevirtual #242                // Method net/minecraft/item/ItemStack.func_190918_g:(I)V
       104: aload_1
       105: ifnull        115
       108: getstatic     #248                // Field electroblob/wizardry/registry/WizardryAdvancementTriggers.special_upgrade:Lelectroblob/wizardry/advancement/CustomAdvancementTrigger;
       111: aload_1
       112: invokevirtual #254                // Method electroblob/wizardry/advancement/CustomAdvancementTrigger.triggerFor:(Lnet/minecraft/entity/player/EntityPlayer;)V
       115: aload_2
       116: areturn
      StackMapTable: number_of_entries = 3
        frame_type = 252 /* append */
          offset_delta = 48
          locals = [ class net/minecraft/item/Item ]
        frame_type = 253 /* append */
          offset_delta = 50
          locals = [ int, int ]
        frame_type = 248 /* chop */
          offset_delta = 15
      LineNumberTable:
        line 123: 0
        line 124: 10
        line 126: 16
        line 128: 48
        line 129: 52
        line 130: 71
        line 131: 78
        line 132: 84
        line 133: 92
        line 136: 99
        line 137: 104
        line 138: 108
        line 144: 115
      LocalVariableTable:
        Start  Length  Slot  Name   Signature
           78      37     6 prevMana   I
           52      63     5 maxUpgrades   I
           16      99     4 specialUpgrade   Lnet/minecraft/item/Item;
            0     117     0  this   Lcom/windanesz/ancientspellcraft/item/ItemBattlemageShield;
            0     117     1 player   Lnet/minecraft/entity/player/EntityPlayer;
            0     117     2 shield   Lnet/minecraft/item/ItemStack;
            0     117     3 upgrade   Lnet/minecraft/item/ItemStack;
    RuntimeVisibleParameterAnnotations:
      parameter 0:
        0: #214()
      parameter 1:
      parameter 2:

  public boolean showTooltip(net.minecraft.item.ItemStack);
    descriptor: (Lnet/minecraft/item/ItemStack;)Z
    flags: ACC_PUBLIC
    Code:
      stack=1, locals=2, args_size=2
         0: iconst_1
         1: ireturn
      LineNumberTable:
        line 149: 0
      LocalVariableTable:
        Start  Length  Slot  Name   Signature
            0       2     0  this   Lcom/windanesz/ancientspellcraft/item/ItemBattlemageShield;
            0       2     1 stack   Lnet/minecraft/item/ItemStack;

  public int getMana(net.minecraft.item.ItemStack);
    descriptor: (Lnet/minecraft/item/ItemStack;)I
    flags: ACC_PUBLIC
    Code:
      stack=3, locals=2, args_size=2
         0: aload_0
         1: aload_1
         2: invokevirtual #158                // Method getManaCapacity:(Lnet/minecraft/item/ItemStack;)I
         5: aload_0
         6: aload_1
         7: invokevirtual #262                // Method getDamage:(Lnet/minecraft/item/ItemStack;)I
        10: isub
        11: ireturn
      LineNumberTable:
        line 154: 0
      LocalVariableTable:
        Start  Length  Slot  Name   Signature
            0      12     0  this   Lcom/windanesz/ancientspellcraft/item/ItemBattlemageShield;
            0      12     1 stack   Lnet/minecraft/item/ItemStack;

  public void setDamage(net.minecraft.item.ItemStack, int);
    descriptor: (Lnet/minecraft/item/ItemStack;I)V
    flags: ACC_PUBLIC
    Code:
      stack=3, locals=3, args_size=3
         0: aload_0
         1: aload_1
         2: iload_2
         3: invokespecial #265                // Method net/minecraft/item/Item.setDamage:(Lnet/minecraft/item/ItemStack;I)V
         6: return
      LineNumberTable:
        line 160: 0
        line 161: 6
      LocalVariableTable:
        Start  Length  Slot  Name   Signature
            0       7     0  this   Lcom/windanesz/ancientspellcraft/item/ItemBattlemageShield;
            0       7     1 stack   Lnet/minecraft/item/ItemStack;
            0       7     2 damage   I

  public void setMana(net.minecraft.item.ItemStack, int);
    descriptor: (Lnet/minecraft/item/ItemStack;I)V
    flags: ACC_PUBLIC
    Code:
      stack=4, locals=3, args_size=3
         0: aload_0
         1: aload_1
         2: aload_0
         3: aload_1
         4: invokevirtual #158                // Method getManaCapacity:(Lnet/minecraft/item/ItemStack;)I
         7: iload_2
         8: isub
         9: invokespecial #265                // Method net/minecraft/item/Item.setDamage:(Lnet/minecraft/item/ItemStack;I)V
        12: return
      LineNumberTable:
        line 166: 0
        line 167: 12
      LocalVariableTable:
        Start  Length  Slot  Name   Signature
            0      13     0  this   Lcom/windanesz/ancientspellcraft/item/ItemBattlemageShield;
            0      13     1 stack   Lnet/minecraft/item/ItemStack;
            0      13     2  mana   I

  public int getManaCapacity(net.minecraft.item.ItemStack);
    descriptor: (Lnet/minecraft/item/ItemStack;)I
    flags: ACC_PUBLIC
    Code:
      stack=2, locals=2, args_size=2
         0: aload_0
         1: aload_1
         2: invokevirtual #268                // Method getMaxDamage:(Lnet/minecraft/item/ItemStack;)I
         5: ireturn
      LineNumberTable:
        line 171: 0
      LocalVariableTable:
        Start  Length  Slot  Name   Signature
            0       6     0  this   Lcom/windanesz/ancientspellcraft/item/ItemBattlemageShield;
            0       6     1 stack   Lnet/minecraft/item/ItemStack;

  public void func_77624_a(net.minecraft.item.ItemStack, net.minecraft.world.World, java.util.List<java.lang.String>, net.minecraft.client.util.ITooltipFlag);
    descriptor: (Lnet/minecraft/item/ItemStack;Lnet/minecraft/world/World;Ljava/util/List;Lnet/minecraft/client/util/ITooltipFlag;)V
    flags: ACC_PUBLIC
    Code:
      stack=8, locals=5, args_size=5
         0: getstatic     #281                // Field electroblob/wizardry/Wizardry.proxy:Lelectroblob/wizardry/CommonProxy;
         3: aload_3
         4: new           #283                // class java/lang/StringBuilder
         7: dup
         8: invokespecial #284                // Method java/lang/StringBuilder."<init>":()V
        11: ldc_w         #286                // String item.
        14: invokevirtual #290                // Method java/lang/StringBuilder.append:(Ljava/lang/String;)Ljava/lang/StringBuilder;
        17: aload_0
        18: invokevirtual #294                // Method getRegistryName:()Lnet/minecraft/util/ResourceLocation;
        21: invokevirtual #297                // Method java/lang/StringBuilder.append:(Ljava/lang/Object;)Ljava/lang/StringBuilder;
        24: ldc_w         #299                // String .desc
        27: invokevirtual #290                // Method java/lang/StringBuilder.append:(Ljava/lang/String;)Ljava/lang/StringBuilder;
        30: invokevirtual #303                // Method java/lang/StringBuilder.toString:()Ljava/lang/String;
        33: iconst_0
        34: anewarray     #305                // class java/lang/Object
        37: invokevirtual #311                // Method electroblob/wizardry/CommonProxy.addMultiLineDescription:(Ljava/util/List;Ljava/lang/String;[Ljava/lang/Object;)V
        40: aload         4
        42: invokeinterface #316,  1          // InterfaceMethod net/minecraft/client/util/ITooltipFlag.func_194127_a:()Z
        47: ifeq          108
        50: aload_3
        51: new           #283                // class java/lang/StringBuilder
        54: dup
        55: invokespecial #284                // Method java/lang/StringBuilder."<init>":()V
        58: ldc_w         #318                // String üś9
        61: invokevirtual #290                // Method java/lang/StringBuilder.append:(Ljava/lang/String;)Ljava/lang/StringBuilder;
        64: ldc_w         #320                // String item.ebwizardry:wand.mana
        67: iconst_2
        68: anewarray     #305                // class java/lang/Object
        71: dup
        72: iconst_0
        73: aload_0
        74: aload_1
        75: invokevirtual #161                // Method getMana:(Lnet/minecraft/item/ItemStack;)I
        78: invokestatic  #326                // Method java/lang/Integer.valueOf:(I)Ljava/lang/Integer;
        81: aastore
        82: dup
        83: iconst_1
        84: aload_0
        85: aload_1
        86: invokevirtual #158                // Method getManaCapacity:(Lnet/minecraft/item/ItemStack;)I
        89: invokestatic  #326                // Method java/lang/Integer.valueOf:(I)Ljava/lang/Integer;
        92: aastore
        93: invokestatic  #332                // Method net/minecraft/client/resources/I18n.func_135052_a:(Ljava/lang/String;[Ljava/lang/Object;)Ljava/lang/String;
        96: invokevirtual #290                // Method java/lang/StringBuilder.append:(Ljava/lang/String;)Ljava/lang/StringBuilder;
        99: invokevirtual #303                // Method java/lang/StringBuilder.toString:()Ljava/lang/String;
       102: invokeinterface #338,  2          // InterfaceMethod java/util/List.add:(Ljava/lang/Object;)Z
       107: pop
       108: return
      StackMapTable: number_of_entries = 1
        frame_type = 251 /* same_frame_extended */
          offset_delta = 108
      LineNumberTable:
        line 180: 0
        line 182: 40
        line 185: 50
        line 186: 75
        line 185: 93
        line 189: 108
      LocalVariableTable:
        Start  Length  Slot  Name   Signature
            0     109     0  this   Lcom/windanesz/ancientspellcraft/item/ItemBattlemageShield;
            0     109     1 stack   Lnet/minecraft/item/ItemStack;
            0     109     2 worldIn   Lnet/minecraft/world/World;
            0     109     3 tooltip   Ljava/util/List;
            0     109     4 advanced   Lnet/minecraft/client/util/ITooltipFlag;
      LocalVariableTypeTable:
        Start  Length  Slot  Name   Signature
            0     109     3 tooltip   Ljava/util/List<Ljava/lang/String;>;
    Signature: #271                         // (Lnet/minecraft/item/ItemStack;Lnet/minecraft/world/World;Ljava/util/List<Ljava/lang/String;>;Lnet/minecraft/client/util/ITooltipFlag;)V
    RuntimeVisibleAnnotations:
      0: #272(#273=e#274.#275)
    RuntimeVisibleParameterAnnotations:
      parameter 0:
      parameter 1:
        0: #214()
      parameter 2:
      parameter 3:

  public net.minecraft.item.EnumAction func_77661_b(net.minecraft.item.ItemStack);
    descriptor: (Lnet/minecraft/item/ItemStack;)Lnet/minecraft/item/EnumAction;
    flags: ACC_PUBLIC
    Code:
      stack=1, locals=2, args_size=2
         0: getstatic     #353                // Field net/minecraft/item/EnumAction.BLOCK:Lnet/minecraft/item/EnumAction;
         3: areturn
      LineNumberTable:
        line 195: 0
      LocalVariableTable:
        Start  Length  Slot  Name   Signature
            0       4     0  this   Lcom/windanesz/ancientspellcraft/item/ItemBattlemageShield;
            0       4     1 stack   Lnet/minecraft/item/ItemStack;

  public int func_77626_a(net.minecraft.item.ItemStack);
    descriptor: (Lnet/minecraft/item/ItemStack;)I
    flags: ACC_PUBLIC
    Code:
      stack=1, locals=2, args_size=2
         0: sipush        20000
         3: ireturn
      LineNumberTable:
        line 202: 0
      LocalVariableTable:
        Start  Length  Slot  Name   Signature
            0       4     0  this   Lcom/windanesz/ancientspellcraft/item/ItemBattlemageShield;
            0       4     1 stack   Lnet/minecraft/item/ItemStack;

  public net.minecraft.util.ActionResult<net.minecraft.item.ItemStack> func_77659_a(net.minecraft.world.World, net.minecraft.entity.player.EntityPlayer, net.minecraft.util.EnumHand);
    descriptor: (Lnet/minecraft/world/World;Lnet/minecraft/entity/player/EntityPlayer;Lnet/minecraft/util/EnumHand;)Lnet/minecraft/util/ActionResult;
    flags: ACC_PUBLIC
    Code:
      stack=7, locals=5, args_size=4
         0: aload_2
         1: aload_3
         2: invokevirtual #363                // Method net/minecraft/entity/player/EntityPlayer.func_184586_b:(Lnet/minecraft/util/EnumHand;)Lnet/minecraft/item/ItemStack;
         5: astore        4
         7: aload_0
         8: aload_2
         9: invokevirtual #367                // Method isBattlemage:(Lnet/minecraft/entity/player/EntityPlayer;)Z
        12: ifne          40
        15: aload_2
        16: ldc_w         #369                // String Only a battlemage can use this
        19: iconst_0
        20: iconst_0
        21: anewarray     #305                // class java/lang/Object
        24: invokestatic  #375                // Method com/windanesz/ancientspellcraft/util/ASUtils.sendMessage:(Lnet/minecraft/entity/Entity;Ljava/lang/String;Z[Ljava/lang/Object;)V
        27: new           #377                // class net/minecraft/util/ActionResult
        30: dup
        31: getstatic     #383                // Field net/minecraft/util/EnumActionResult.FAIL:Lnet/minecraft/util/EnumActionResult;
        34: aload         4
        36: invokespecial #386                // Method net/minecraft/util/ActionResult."<init>":(Lnet/minecraft/util/EnumActionResult;Ljava/lang/Object;)V
        39: areturn
        40: aload_3
        41: getstatic     #392                // Field net/minecraft/util/EnumHand.MAIN_HAND:Lnet/minecraft/util/EnumHand;
        44: if_acmpne     80
        47: aload_2
        48: invokevirtual #395                // Method net/minecraft/entity/player/EntityPlayer.func_70093_af:()Z
        51: ifeq          80
        54: aload_2
        55: getstatic     #401                // Field com/windanesz/ancientspellcraft/AncientSpellcraft.instance:Lcom/windanesz/ancientspellcraft/AncientSpellcraft;
        58: getstatic     #406                // Field com/windanesz/ancientspellcraft/client/gui/GuiHandlerAS.BATTLEMAGE_SHIELD:I
        61: aload_2
        62: getfield      #409                // Field net/minecraft/entity/player/EntityPlayer.field_70170_p:Lnet/minecraft/world/World;
        65: iconst_0
        66: iconst_0
        67: iconst_0
        68: invokevirtual #413                // Method net/minecraft/entity/player/EntityPlayer.openGui:(Ljava/lang/Object;ILnet/minecraft/world/World;III)V
        71: getstatic     #416                // Field net/minecraft/util/EnumActionResult.SUCCESS:Lnet/minecraft/util/EnumActionResult;
        74: aload         4
        76: invokestatic  #420                // Method net/minecraft/util/ActionResult.newResult:(Lnet/minecraft/util/EnumActionResult;Ljava/lang/Object;)Lnet/minecraft/util/ActionResult;
        79: areturn
        80: aload_0
        81: aload         4
        83: invokevirtual #423                // Method isManaEmpty:(Lnet/minecraft/item/ItemStack;)Z
        86: ifeq          102
        89: new           #377                // class net/minecraft/util/ActionResult
        92: dup
        93: getstatic     #383                // Field net/minecraft/util/EnumActionResult.FAIL:Lnet/minecraft/util/EnumActionResult;
        96: aload         4
        98: invokespecial #386                // Method net/minecraft/util/ActionResult."<init>":(Lnet/minecraft/util/EnumActionResult;Ljava/lang/Object;)V
       101: areturn
       102: aload_2
       103: aload_3
       104: invokevirtual #427                // Method net/minecraft/entity/player/EntityPlayer.func_184598_c:(Lnet/minecraft/util/EnumHand;)V
       107: new           #377                // class net/minecraft/util/ActionResult
       110: dup
       111: getstatic     #416                // Field net/minecraft/util/EnumActionResult.SUCCESS:Lnet/minecraft/util/EnumActionResult;
       114: aload         4
       116: invokespecial #386                // Method net/minecraft/util/ActionResult."<init>":(Lnet/minecraft/util/EnumActionResult;Ljava/lang/Object;)V
       119: areturn
      StackMapTable: number_of_entries = 3
        frame_type = 252 /* append */
          offset_delta = 40
          locals = [ class net/minecraft/item/ItemStack ]
        frame_type = 39 /* same */
        frame_type = 21 /* same */
      LineNumberTable:
        line 209: 0
        line 211: 7
        line 212: 15
        line 213: 27
        line 216: 40
        line 218: 54
        line 219: 71
        line 222: 80
        line 223: 89
        line 232: 102
        line 233: 107
      LocalVariableTable:
        Start  Length  Slot  Name   Signature
            0     120     0  this   Lcom/windanesz/ancientspellcraft/item/ItemBattlemageShield;
            0     120     1 worldIn   Lnet/minecraft/world/World;
            0     120     2 player   Lnet/minecraft/entity/player/EntityPlayer;
            0     120     3  hand   Lnet/minecraft/util/EnumHand;
            7     113     4 stack   Lnet/minecraft/item/ItemStack;
    Signature: #357                         // (Lnet/minecraft/world/World;Lnet/minecraft/entity/player/EntityPlayer;Lnet/minecraft/util/EnumHand;)Lnet/minecraft/util/ActionResult<Lnet/minecraft/item/ItemStack;>;

  public boolean canContinueUsing(net.minecraft.item.ItemStack, net.minecraft.item.ItemStack);
    descriptor: (Lnet/minecraft/item/ItemStack;Lnet/minecraft/item/ItemStack;)Z
    flags: ACC_PUBLIC
    Code:
      stack=3, locals=3, args_size=3
         0: aload_1
         1: aload_2
         2: invokestatic  #432                // Method net/minecraft/item/ItemStack.func_185132_d:(Lnet/minecraft/item/ItemStack;Lnet/minecraft/item/ItemStack;)Z
         5: ifeq          10
         8: iconst_1
         9: ireturn
        10: aload_0
        11: aload_1
        12: aload_2
        13: invokespecial #434                // Method net/minecraft/item/Item.canContinueUsing:(Lnet/minecraft/item/ItemStack;Lnet/minecraft/item/ItemStack;)Z
        16: ireturn
      StackMapTable: number_of_entries = 1
        frame_type = 10 /* same */
      LineNumberTable:
        line 242: 0
        line 243: 10
      LocalVariableTable:
        Start  Length  Slot  Name   Signature
            0      17     0  this   Lcom/windanesz/ancientspellcraft/item/ItemBattlemageShield;
            0      17     1 oldStack   Lnet/minecraft/item/ItemStack;
            0      17     2 newStack   Lnet/minecraft/item/ItemStack;

  public void onUsingTick(net.minecraft.item.ItemStack, net.minecraft.entity.EntityLivingBase, int);
    descriptor: (Lnet/minecraft/item/ItemStack;Lnet/minecraft/entity/EntityLivingBase;I)V
    flags: ACC_PUBLIC
    Code:
      stack=4, locals=4, args_size=4
         0: aload_0
         1: aload_1
         2: aload_2
         3: iload_3
         4: invokespecial #440                // Method net/minecraft/item/Item.onUsingTick:(Lnet/minecraft/item/ItemStack;Lnet/minecraft/entity/EntityLivingBase;I)V
         7: return
      LineNumberTable:
        line 248: 0
        line 249: 7
      LocalVariableTable:
        Start  Length  Slot  Name   Signature
            0       8     0  this   Lcom/windanesz/ancientspellcraft/item/ItemBattlemageShield;
            0       8     1 stack   Lnet/minecraft/item/ItemStack;
            0       8     2  user   Lnet/minecraft/entity/EntityLivingBase;
            0       8     3 count   I

  public boolean isBattlemage(net.minecraft.entity.player.EntityPlayer);
    descriptor: (Lnet/minecraft/entity/player/EntityPlayer;)Z
    flags: ACC_PUBLIC
    Code:
      stack=3, locals=2, args_size=2
         0: aload_1
         1: aconst_null
         2: getstatic     #447                // Field electroblob/wizardry/item/ItemWizardArmour$ArmourClass.BATTLEMAGE:Lelectroblob/wizardry/item/ItemWizardArmour$ArmourClass;
         5: invokestatic  #453                // Method com/windanesz/ancientspellcraft/util/WizardArmourUtils.isWearingFullSet:(Lnet/minecraft/entity/EntityLivingBase;Lelectroblob/wizardry/constants/Element;Lelectroblob/wizardry/item/ItemWizardArmour$ArmourClass;)Z
         8: ireturn
      LineNumberTable:
        line 252: 0
      LocalVariableTable:
        Start  Length  Slot  Name   Signature
            0       9     0  this   Lcom/windanesz/ancientspellcraft/item/ItemBattlemageShield;
            0       9     1 player   Lnet/minecraft/entity/player/EntityPlayer;

  public java.lang.String func_77653_i(net.minecraft.item.ItemStack);
    descriptor: (Lnet/minecraft/item/ItemStack;)Ljava/lang/String;
    flags: ACC_PUBLIC
    Code:
      stack=2, locals=2, args_size=2
         0: aload_0
         1: aload_1
         2: invokespecial #457                // Method net/minecraft/item/Item.func_77653_i:(Lnet/minecraft/item/ItemStack;)Ljava/lang/String;
         5: areturn
      LineNumberTable:
        line 257: 0
      LocalVariableTable:
        Start  Length  Slot  Name   Signature
            0       6     0  this   Lcom/windanesz/ancientspellcraft/item/ItemBattlemageShield;
            0       6     1 stack   Lnet/minecraft/item/ItemStack;

  public boolean shouldCauseReequipAnimation(net.minecraft.item.ItemStack, net.minecraft.item.ItemStack, boolean);
    descriptor: (Lnet/minecraft/item/ItemStack;Lnet/minecraft/item/ItemStack;Z)Z
    flags: ACC_PUBLIC
    Code:
      stack=4, locals=4, args_size=4
         0: aload_1
         1: invokevirtual #462                // Method net/minecraft/item/ItemStack.func_190926_b:()Z
         4: ifeq          14
         7: aload_2
         8: invokevirtual #462                // Method net/minecraft/item/ItemStack.func_190926_b:()Z
        11: ifne          31
        14: aload_1
        15: invokevirtual #217                // Method net/minecraft/item/ItemStack.func_77973_b:()Lnet/minecraft/item/Item;
        18: aload_2
        19: invokevirtual #217                // Method net/minecraft/item/ItemStack.func_77973_b:()Lnet/minecraft/item/Item;
        22: if_acmpne     31
        25: iload_3
        26: ifne          31
        29: iconst_0
        30: ireturn
        31: aload_0
        32: aload_1
        33: aload_2
        34: iload_3
        35: invokespecial #464                // Method net/minecraft/item/Item.shouldCauseReequipAnimation:(Lnet/minecraft/item/ItemStack;Lnet/minecraft/item/ItemStack;Z)Z
        38: ireturn
      StackMapTable: number_of_entries = 2
        frame_type = 14 /* same */
        frame_type = 16 /* same */
      LineNumberTable:
        line 261: 0
        line 263: 14
        line 264: 29
        line 268: 31
      LocalVariableTable:
        Start  Length  Slot  Name   Signature
            0      39     0  this   Lcom/windanesz/ancientspellcraft/item/ItemBattlemageShield;
            0      39     1 oldStack   Lnet/minecraft/item/ItemStack;
            0      39     2 newStack   Lnet/minecraft/item/ItemStack;
            0      39     3 slotChanged   Z

  public boolean cast(net.minecraft.item.ItemStack, electroblob.wizardry.spell.Spell, net.minecraft.entity.player.EntityPlayer, net.minecraft.util.EnumHand, int, electroblob.wizardry.util.SpellModifiers);
    descriptor: (Lnet/minecraft/item/ItemStack;Lelectroblob/wizardry/spell/Spell;Lnet/minecraft/entity/player/EntityPlayer;Lnet/minecraft/util/EnumHand;ILelectroblob/wizardry/util/SpellModifiers;)Z
    flags: ACC_PUBLIC
    Code:
      stack=7, locals=9, args_size=7
         0: aload_3
         1: getfield      #409                // Field net/minecraft/entity/player/EntityPlayer.field_70170_p:Lnet/minecraft/world/World;
         4: astore        7
         6: aload         7
         8: getfield      #472                // Field net/minecraft/world/World.field_72995_K:Z
        11: ifeq          30
        14: aload_2
        15: getfield      #477                // Field electroblob/wizardry/spell/Spell.isContinuous:Z
        18: ifne          30
        21: aload_2
        22: invokevirtual #480                // Method electroblob/wizardry/spell/Spell.requiresPacket:()Z
        25: ifeq          30
        28: iconst_0
        29: ireturn
        30: aload_2
        31: aload         7
        33: aload_3
        34: aload         4
        36: iload         5
        38: aload         6
        40: invokevirtual #483                // Method electroblob/wizardry/spell/Spell.cast:(Lnet/minecraft/world/World;Lnet/minecraft/entity/player/EntityPlayer;Lnet/minecraft/util/EnumHand;ILelectroblob/wizardry/util/SpellModifiers;)Z
        43: ifeq          130
        46: iload         5
        48: ifne          72
        51: getstatic     #489                // Field net/minecraftforge/common/MinecraftForge.EVENT_BUS:Lnet/minecraftforge/fml/common/eventhandler/EventBus;
        54: new           #17                 // class electroblob/wizardry/event/SpellCastEvent$Post
        57: dup
        58: getstatic     #493                // Field electroblob/wizardry/event/SpellCastEvent$Source.OTHER:Lelectroblob/wizardry/event/SpellCastEvent$Source;
        61: aload_2
        62: aload_3
        63: aload         6
        65: invokespecial #496                // Method electroblob/wizardry/event/SpellCastEvent$Post."<init>":(Lelectroblob/wizardry/event/SpellCastEvent$Source;Lelectroblob/wizardry/spell/Spell;Lnet/minecraft/entity/EntityLivingBase;Lelectroblob/wizardry/util/SpellModifiers;)V
        68: invokevirtual #502                // Method net/minecraftforge/fml/common/eventhandler/EventBus.post:(Lnet/minecraftforge/fml/common/eventhandler/Event;)Z
        71: pop
        72: aload         7
        74: getfield      #472                // Field net/minecraft/world/World.field_72995_K:Z
        77: ifne          128
        80: aload_2
        81: getfield      #477                // Field electroblob/wizardry/spell/Spell.isContinuous:Z
        84: ifne          128
        87: aload_2
        88: invokevirtual #480                // Method electroblob/wizardry/spell/Spell.requiresPacket:()Z
        91: ifeq          128
        94: new           #22                 // class electroblob/wizardry/packet/PacketCastSpell$Message
        97: dup
        98: aload_3
        99: invokevirtual #505                // Method net/minecraft/entity/player/EntityPlayer.func_145782_y:()I
       102: aload         4
       104: aload_2
       105: aload         6
       107: invokespecial #508                // Method electroblob/wizardry/packet/PacketCastSpell$Message."<init>":(ILnet/minecraft/util/EnumHand;Lelectroblob/wizardry/spell/Spell;Lelectroblob/wizardry/util/SpellModifiers;)V
       110: astore        8
       112: getstatic     #514                // Field electroblob/wizardry/packet/WizardryPacketHandler.net:Lnet/minecraftforge/fml/common/network/simpleimpl/SimpleNetworkWrapper;
       115: aload         8
       117: aload         7
       119: getfield      #518                // Field net/minecraft/world/World.field_73011_w:Lnet/minecraft/world/WorldProvider;
       122: invokevirtual #523                // Method net/minecraft/world/WorldProvider.getDimension:()I
       125: invokevirtual #529                // Method net/minecraftforge/fml/common/network/simpleimpl/SimpleNetworkWrapper.sendToDimension:(Lnet/minecraftforge/fml/common/network/simpleimpl/IMessage;I)V
       128: iconst_1
       129: ireturn
       130: iconst_0
       131: ireturn
      StackMapTable: number_of_entries = 4
        frame_type = 252 /* append */
          offset_delta = 30
          locals = [ class net/minecraft/world/World ]
        frame_type = 41 /* same */
        frame_type = 55 /* same */
        frame_type = 1 /* same */
      LineNumberTable:
        line 274: 0
        line 276: 6
        line 278: 30
        line 280: 46
        line 282: 72
        line 285: 80
        line 287: 94
        line 288: 112
        line 291: 128
        line 293: 130
      LocalVariableTable:
        Start  Length  Slot  Name   Signature
          112      16     8   msg   Lnet/minecraftforge/fml/common/network/simpleimpl/IMessage;
            0     132     0  this   Lcom/windanesz/ancientspellcraft/item/ItemBattlemageShield;
            0     132     1 stack   Lnet/minecraft/item/ItemStack;
            0     132     2 spell   Lelectroblob/wizardry/spell/Spell;
            0     132     3 caster   Lnet/minecraft/entity/player/EntityPlayer;
            0     132     4  hand   Lnet/minecraft/util/EnumHand;
            0     132     5 castingTick   I
            0     132     6 modifiers   Lelectroblob/wizardry/util/SpellModifiers;
            6     126     7 world   Lnet/minecraft/world/World;

  public electroblob.wizardry.spell.Spell getCurrentSpell(net.minecraft.item.ItemStack);
    descriptor: (Lnet/minecraft/item/ItemStack;)Lelectroblob/wizardry/spell/Spell;
    flags: ACC_PUBLIC
    Code:
      stack=1, locals=2, args_size=2
         0: getstatic     #545                // Field electroblob/wizardry/registry/Spells.shield:Lelectroblob/wizardry/spell/Spell;
         3: areturn
      LineNumberTable:
        line 299: 0
      LocalVariableTable:
        Start  Length  Slot  Name   Signature
            0       4     0  this   Lcom/windanesz/ancientspellcraft/item/ItemBattlemageShield;
            0       4     1 stack   Lnet/minecraft/item/ItemStack;
    RuntimeVisibleAnnotations:
      0: #541()

  public boolean showSpellHUD(net.minecraft.entity.player.EntityPlayer, net.minecraft.item.ItemStack);
    descriptor: (Lnet/minecraft/entity/player/EntityPlayer;Lnet/minecraft/item/ItemStack;)Z
    flags: ACC_PUBLIC
    Code:
      stack=1, locals=3, args_size=3
         0: iconst_0
         1: ireturn
      LineNumberTable:
        line 304: 0
      LocalVariableTable:
        Start  Length  Slot  Name   Signature
            0       2     0  this   Lcom/windanesz/ancientspellcraft/item/ItemBattlemageShield;
            0       2     1 player   Lnet/minecraft/entity/player/EntityPlayer;
            0       2     2 stack   Lnet/minecraft/item/ItemStack;

  public boolean canCast(net.minecraft.item.ItemStack, electroblob.wizardry.spell.Spell, net.minecraft.entity.player.EntityPlayer, net.minecraft.util.EnumHand, int, electroblob.wizardry.util.SpellModifiers);
    descriptor: (Lnet/minecraft/item/ItemStack;Lelectroblob/wizardry/spell/Spell;Lnet/minecraft/entity/player/EntityPlayer;Lnet/minecraft/util/EnumHand;ILelectroblob/wizardry/util/SpellModifiers;)Z
    flags: ACC_PUBLIC
    Code:
      stack=1, locals=7, args_size=7
         0: iconst_1
         1: ireturn
      LineNumberTable:
        line 310: 0
      LocalVariableTable:
        Start  Length  Slot  Name   Signature
            0       2     0  this   Lcom/windanesz/ancientspellcraft/item/ItemBattlemageShield;
            0       2     1 stack   Lnet/minecraft/item/ItemStack;
            0       2     2 spell   Lelectroblob/wizardry/spell/Spell;
            0       2     3 caster   Lnet/minecraft/entity/player/EntityPlayer;
            0       2     4  hand   Lnet/minecraft/util/EnumHand;
            0       2     5 castingTick   I
            0       2     6 modifiers   Lelectroblob/wizardry/util/SpellModifiers;

  public com.google.common.collect.Multimap<java.lang.String, net.minecraft.entity.ai.attributes.AttributeModifier> func_111205_h(net.minecraft.inventory.EntityEquipmentSlot);
    descriptor: (Lnet/minecraft/inventory/EntityEquipmentSlot;)Lcom/google/common/collect/Multimap;
    flags: ACC_PUBLIC
    Code:
      stack=9, locals=3, args_size=2
         0: aload_0
         1: aload_1
         2: invokespecial #553                // Method net/minecraft/item/Item.func_111205_h:(Lnet/minecraft/inventory/EntityEquipmentSlot;)Lcom/google/common/collect/Multimap;
         5: astore_2
         6: aload_1
         7: getstatic     #559                // Field net/minecraft/inventory/EntityEquipmentSlot.OFFHAND:Lnet/minecraft/inventory/EntityEquipmentSlot;
        10: if_acmpne     85
        13: aload_2
        14: getstatic     #565                // Field net/minecraft/entity/SharedMonsterAttributes.field_188791_g:Lnet/minecraft/entity/ai/attributes/IAttribute;
        17: invokeinterface #570,  1          // InterfaceMethod net/minecraft/entity/ai/attributes/IAttribute.func_111108_a:()Ljava/lang/String;
        22: new           #572                // class net/minecraft/entity/ai/attributes/AttributeModifier
        25: dup
        26: getstatic     #574                // Field SHIELD_ARMOR_BONUS:Ljava/util/UUID;
        29: ldc_w         #576                // String Armor modifier
        32: getstatic     #68                 // Field com/windanesz/ancientspellcraft/Settings.generalSettings:Lcom/windanesz/ancientspellcraft/Settings$GeneralSettings;
        35: getfield      #580                // Field com/windanesz/ancientspellcraft/Settings$GeneralSettings.runic_shield_armor:F
        38: f2d
        39: iconst_0
        40: invokespecial #583                // Method net/minecraft/entity/ai/attributes/AttributeModifier."<init>":(Ljava/util/UUID;Ljava/lang/String;DI)V
        43: invokeinterface #589,  3          // InterfaceMethod com/google/common/collect/Multimap.put:(Ljava/lang/Object;Ljava/lang/Object;)Z
        48: pop
        49: aload_2
        50: getstatic     #592                // Field net/minecraft/entity/SharedMonsterAttributes.field_189429_h:Lnet/minecraft/entity/ai/attributes/IAttribute;
        53: invokeinterface #570,  1          // InterfaceMethod net/minecraft/entity/ai/attributes/IAttribute.func_111108_a:()Ljava/lang/String;
        58: new           #572                // class net/minecraft/entity/ai/attributes/AttributeModifier
        61: dup
        62: getstatic     #594                // Field SHIELD_TOUGHNESS_BONUS:Ljava/util/UUID;
        65: ldc_w         #596                // String Armor toughness
        68: getstatic     #68                 // Field com/windanesz/ancientspellcraft/Settings.generalSettings:Lcom/windanesz/ancientspellcraft/Settings$GeneralSettings;
        71: getfield      #599                // Field com/windanesz/ancientspellcraft/Settings$GeneralSettings.runic_shield_armor_toughness:F
        74: f2d
        75: iconst_0
        76: invokespecial #583                // Method net/minecraft/entity/ai/attributes/AttributeModifier."<init>":(Ljava/util/UUID;Ljava/lang/String;DI)V
        79: invokeinterface #589,  3          // InterfaceMethod com/google/common/collect/Multimap.put:(Ljava/lang/Object;Ljava/lang/Object;)Z
        84: pop
        85: aload_2
        86: areturn
      StackMapTable: number_of_entries = 1
        frame_type = 252 /* append */
          offset_delta = 85
          locals = [ class com/google/common/collect/Multimap ]
      LineNumberTable:
        line 315: 0
        line 316: 6
        line 318: 13
        line 320: 49
        line 324: 85
      LocalVariableTable:
        Start  Length  Slot  Name   Signature
            0      87     0  this   Lcom/windanesz/ancientspellcraft/item/ItemBattlemageShield;
            0      87     1  slot   Lnet/minecraft/inventory/EntityEquipmentSlot;
            6      81     2 multimap   Lcom/google/common/collect/Multimap;
      LocalVariableTypeTable:
        Start  Length  Slot  Name   Signature
            6      81     2 multimap   Lcom/google/common/collect/Multimap<Ljava/lang/String;Lnet/minecraft/entity/ai/attributes/AttributeModifier;>;
    Signature: #551                         // (Lnet/minecraft/inventory/EntityEquipmentSlot;)Lcom/google/common/collect/Multimap<Ljava/lang/String;Lnet/minecraft/entity/ai/attributes/AttributeModifier;>;

  public void func_77663_a(net.minecraft.item.ItemStack, net.minecraft.world.World, net.minecraft.entity.Entity, int, boolean);
    descriptor: (Lnet/minecraft/item/ItemStack;Lnet/minecraft/world/World;Lnet/minecraft/entity/Entity;IZ)V
    flags: ACC_PUBLIC
    Code:
      stack=6, locals=10, args_size=6
         0: aload_0
         1: aload_1
         2: aload_2
         3: aload_3
         4: iload         4
         6: iload         5
         8: invokespecial #607                // Method net/minecraft/item/Item.func_77663_a:(Lnet/minecraft/item/ItemStack;Lnet/minecraft/world/World;Lnet/minecraft/entity/Entity;IZ)V
        11: aload_3
        12: instanceof    #359                // class net/minecraft/entity/player/EntityPlayer
        15: ifeq          227
        18: aload_0
        19: aload_3
        20: checkcast     #359                // class net/minecraft/entity/player/EntityPlayer
        23: invokevirtual #367                // Method isBattlemage:(Lnet/minecraft/entity/player/EntityPlayer;)Z
        26: ifeq          227
        29: aload_3
        30: checkcast     #359                // class net/minecraft/entity/player/EntityPlayer
        33: astore        6
        35: aload         6
        37: invokevirtual #610                // Method net/minecraft/entity/player/EntityPlayer.func_184592_cb:()Lnet/minecraft/item/ItemStack;
        40: aload_1
        41: invokestatic  #148                // Method net/minecraft/item/ItemStack.func_77989_b:(Lnet/minecraft/item/ItemStack;Lnet/minecraft/item/ItemStack;)Z
        44: ifne          48
        47: return
        48: aload_1
        49: invokevirtual #217                // Method net/minecraft/item/ItemStack.func_77973_b:()Lnet/minecraft/item/Item;
        52: instanceof    #2                  // class com/windanesz/ancientspellcraft/item/ItemBattlemageShield
        55: ifeq          145
        58: aload_1
        59: invokevirtual #613                // Method net/minecraft/item/ItemStack.func_77942_o:()Z
        62: ifeq          145
        65: aload_1
        66: invokevirtual #617                // Method net/minecraft/item/ItemStack.func_77978_p:()Lnet/minecraft/nbt/NBTTagCompound;
        69: astore        7
        71: aload         7
        73: ldc_w         #619                // String Items
        76: invokevirtual #625                // Method net/minecraft/nbt/NBTTagCompound.func_74764_b:(Ljava/lang/String;)Z
        79: ifeq          145
        82: aload_1
        83: invokevirtual #617                // Method net/minecraft/item/ItemStack.func_77978_p:()Lnet/minecraft/nbt/NBTTagCompound;
        86: ldc_w         #619                // String Items
        89: bipush        10
        91: invokevirtual #629                // Method net/minecraft/nbt/NBTTagCompound.func_150295_c:(Ljava/lang/String;I)Lnet/minecraft/nbt/NBTTagList;
        94: invokevirtual #634                // Method net/minecraft/nbt/NBTTagList.func_74745_c:()I
        97: istore        8
        99: iconst_0
       100: istore        9
       102: iload         9
       104: iload         8
       106: if_icmpge     145
       109: aload_0
       110: new           #133                // class net/minecraft/item/ItemStack
       113: dup
       114: aload_1
       115: invokevirtual #617                // Method net/minecraft/item/ItemStack.func_77978_p:()Lnet/minecraft/nbt/NBTTagCompound;
       118: ldc_w         #619                // String Items
       121: bipush        10
       123: invokevirtual #629                // Method net/minecraft/nbt/NBTTagCompound.func_150295_c:(Ljava/lang/String;I)Lnet/minecraft/nbt/NBTTagList;
       126: iload         9
       128: invokevirtual #638                // Method net/minecraft/nbt/NBTTagList.func_150305_b:(I)Lnet/minecraft/nbt/NBTTagCompound;
       131: invokespecial #641                // Method net/minecraft/item/ItemStack."<init>":(Lnet/minecraft/nbt/NBTTagCompound;)V
       134: aload         6
       136: invokevirtual #645                // Method tickArtefact:(Lnet/minecraft/item/ItemStack;Lnet/minecraft/entity/player/EntityPlayer;)V
       139: iinc          9, 1
       142: goto          102
       145: aload_2
       146: getfield      #472                // Field net/minecraft/world/World.field_72995_K:Z
       149: ifne          185
       152: aload_0
       153: aload_1
       154: invokevirtual #155                // Method isManaFull:(Lnet/minecraft/item/ItemStack;)Z
       157: ifne          185
       160: aload_2
       161: invokevirtual #649                // Method net/minecraft/world/World.func_82737_E:()J
       164: ldc2_w        #650                // long 50l
       167: lrem
       168: lconst_0
       169: lcmp
       170: ifne          185
       173: aload_0
       174: aload_1
       175: aload_1
       176: getstatic     #227                // Field electroblob/wizardry/registry/WizardryItems.condenser_upgrade:Lnet/minecraft/item/Item;
       179: invokestatic  #212                // Method electroblob/wizardry/util/WandHelper.getUpgradeLevel:(Lnet/minecraft/item/ItemStack;Lnet/minecraft/item/Item;)I
       182: invokevirtual #169                // Method rechargeMana:(Lnet/minecraft/item/ItemStack;I)V
       185: aload_2
       186: getfield      #472                // Field net/minecraft/world/World.field_72995_K:Z
       189: ifne          227
       192: aload         6
       194: invokevirtual #655                // Method net/minecraft/entity/player/EntityPlayer.func_184811_cZ:()Lnet/minecraft/util/CooldownTracker;
       197: aload_1
       198: invokevirtual #217                // Method net/minecraft/item/ItemStack.func_77973_b:()Lnet/minecraft/item/Item;
       201: invokevirtual #660                // Method net/minecraft/util/CooldownTracker.func_185141_a:(Lnet/minecraft/item/Item;)Z
       204: ifeq          227
       207: aload         6
       209: getstatic     #663                // Field com/windanesz/ancientspellcraft/registry/ASItems.charm_glyph_shield_disable:Lnet/minecraft/item/Item;
       212: invokestatic  #669                // Method electroblob/wizardry/item/ItemArtefact.isArtefactActive:(Lnet/minecraft/entity/player/EntityPlayer;Lnet/minecraft/item/Item;)Z
       215: ifeq          227
       218: aload         6
       220: invokevirtual #655                // Method net/minecraft/entity/player/EntityPlayer.func_184811_cZ:()Lnet/minecraft/util/CooldownTracker;
       223: aload_0
       224: invokevirtual #672                // Method net/minecraft/util/CooldownTracker.func_185142_b:(Lnet/minecraft/item/Item;)V
       227: return
      StackMapTable: number_of_entries = 5
        frame_type = 252 /* append */
          offset_delta = 48
          locals = [ class net/minecraft/entity/player/EntityPlayer ]
        frame_type = 254 /* append */
          offset_delta = 53
          locals = [ class net/minecraft/nbt/NBTTagCompound, int, int ]
        frame_type = 248 /* chop */
          offset_delta = 42
        frame_type = 39 /* same */
        frame_type = 250 /* chop */
          offset_delta = 41
      LineNumberTable:
        line 330: 0
        line 332: 11
        line 334: 29
        line 336: 35
        line 337: 47
        line 340: 48
        line 341: 65
        line 342: 71
        line 343: 82
        line 345: 99
        line 346: 109
        line 345: 139
        line 351: 145
        line 352: 173
        line 355: 185
        line 356: 218
        line 360: 227
      LocalVariableTable:
        Start  Length  Slot  Name   Signature
          102      43     9     i   I
           99      46     8 count   I
           71      74     7   nbt   Lnet/minecraft/nbt/NBTTagCompound;
           35     192     6 player   Lnet/minecraft/entity/player/EntityPlayer;
            0     228     0  this   Lcom/windanesz/ancientspellcraft/item/ItemBattlemageShield;
            0     228     1 stack   Lnet/minecraft/item/ItemStack;
            0     228     2 world   Lnet/minecraft/world/World;
            0     228     3 entity   Lnet/minecraft/entity/Entity;
            0     228     4 itemSlot   I
            0     228     5 isSelected   Z

  public static java.util.List<net.minecraft.item.ItemStack> getArtefacts(net.minecraft.item.ItemStack);
    descriptor: (Lnet/minecraft/item/ItemStack;)Ljava/util/List;
    flags: ACC_PUBLIC, ACC_STATIC
    Code:
      stack=6, locals=5, args_size=1
         0: new           #684                // class java/util/ArrayList
         3: dup
         4: invokespecial #685                // Method java/util/ArrayList."<init>":()V
         7: astore_1
         8: aload_0
         9: invokevirtual #217                // Method net/minecraft/item/ItemStack.func_77973_b:()Lnet/minecraft/item/Item;
        12: instanceof    #2                  // class com/windanesz/ancientspellcraft/item/ItemBattlemageShield
        15: ifeq          102
        18: aload_0
        19: invokevirtual #613                // Method net/minecraft/item/ItemStack.func_77942_o:()Z
        22: ifeq          102
        25: aload_0
        26: invokevirtual #617                // Method net/minecraft/item/ItemStack.func_77978_p:()Lnet/minecraft/nbt/NBTTagCompound;
        29: astore_2
        30: aload_2
        31: ldc_w         #619                // String Items
        34: invokevirtual #625                // Method net/minecraft/nbt/NBTTagCompound.func_74764_b:(Ljava/lang/String;)Z
        37: ifeq          102
        40: aload_0
        41: invokevirtual #617                // Method net/minecraft/item/ItemStack.func_77978_p:()Lnet/minecraft/nbt/NBTTagCompound;
        44: ldc_w         #619                // String Items
        47: bipush        10
        49: invokevirtual #629                // Method net/minecraft/nbt/NBTTagCompound.func_150295_c:(Ljava/lang/String;I)Lnet/minecraft/nbt/NBTTagList;
        52: invokevirtual #634                // Method net/minecraft/nbt/NBTTagList.func_74745_c:()I
        55: istore_3
        56: iconst_0
        57: istore        4
        59: iload         4
        61: iload_3
        62: if_icmpge     102
        65: aload_1
        66: new           #133                // class net/minecraft/item/ItemStack
        69: dup
        70: aload_0
        71: invokevirtual #617                // Method net/minecraft/item/ItemStack.func_77978_p:()Lnet/minecraft/nbt/NBTTagCompound;
        74: ldc_w         #619                // String Items
        77: bipush        10
        79: invokevirtual #629                // Method net/minecraft/nbt/NBTTagCompound.func_150295_c:(Ljava/lang/String;I)Lnet/minecraft/nbt/NBTTagList;
        82: iload         4
        84: invokevirtual #638                // Method net/minecraft/nbt/NBTTagList.func_150305_b:(I)Lnet/minecraft/nbt/NBTTagCompound;
        87: invokespecial #641                // Method net/minecraft/item/ItemStack."<init>":(Lnet/minecraft/nbt/NBTTagCompound;)V
        90: invokeinterface #338,  2          // InterfaceMethod java/util/List.add:(Ljava/lang/Object;)Z
        95: pop
        96: iinc          4, 1
        99: goto          59
       102: aload_1
       103: areturn
      StackMapTable: number_of_entries = 2
        frame_type = 255 /* full_frame */
          offset_delta = 59
          locals = [ class net/minecraft/item/ItemStack, class java/util/List, class net/minecraft/nbt/NBTTagCompound, int, int ]
          stack = []
        frame_type = 248 /* chop */
          offset_delta = 42
      LineNumberTable:
        line 363: 0
        line 364: 8
        line 365: 25
        line 366: 30
        line 367: 40
        line 369: 56
        line 370: 65
        line 369: 96
        line 374: 102
      LocalVariableTable:
        Start  Length  Slot  Name   Signature
           59      43     4     i   I
           56      46     3 count   I
           30      72     2   nbt   Lnet/minecraft/nbt/NBTTagCompound;
            0     104     0 shield   Lnet/minecraft/item/ItemStack;
            8      96     1 artefacts   Ljava/util/List;
      LocalVariableTypeTable:
        Start  Length  Slot  Name   Signature
            8      96     1 artefacts   Ljava/util/List<Lnet/minecraft/item/ItemStack;>;
    Signature: #682                         // (Lnet/minecraft/item/ItemStack;)Ljava/util/List<Lnet/minecraft/item/ItemStack;>;

  public void tickArtefact(net.minecraft.item.ItemStack, net.minecraft.entity.player.EntityPlayer);
    descriptor: (Lnet/minecraft/item/ItemStack;Lnet/minecraft/entity/player/EntityPlayer;)V
    flags: ACC_PUBLIC
    Code:
      stack=3, locals=3, args_size=3
         0: aload_1
         1: invokevirtual #217                // Method net/minecraft/item/ItemStack.func_77973_b:()Lnet/minecraft/item/Item;
         4: instanceof    #689                // class com/windanesz/ancientspellcraft/item/ITickableArtefact
         7: ifeq          24
        10: aload_1
        11: invokevirtual #217                // Method net/minecraft/item/ItemStack.func_77973_b:()Lnet/minecraft/item/Item;
        14: checkcast     #689                // class com/windanesz/ancientspellcraft/item/ITickableArtefact
        17: aload_1
        18: aload_2
        19: invokeinterface #693,  3          // InterfaceMethod com/windanesz/ancientspellcraft/item/ITickableArtefact.onWornTick:(Lnet/minecraft/item/ItemStack;Lnet/minecraft/entity/EntityLivingBase;)V
        24: return
      StackMapTable: number_of_entries = 1
        frame_type = 24 /* same */
      LineNumberTable:
        line 378: 0
        line 379: 10
        line 381: 24
      LocalVariableTable:
        Start  Length  Slot  Name   Signature
            0      25     0  this   Lcom/windanesz/ancientspellcraft/item/ItemBattlemageShield;
            0      25     1 stack   Lnet/minecraft/item/ItemStack;
            0      25     2 player   Lnet/minecraft/entity/player/EntityPlayer;

  public boolean func_77616_k(net.minecraft.item.ItemStack);
    descriptor: (Lnet/minecraft/item/ItemStack;)Z
    flags: ACC_PUBLIC
    Code:
      stack=1, locals=2, args_size=2
         0: iconst_0
         1: ireturn
      LineNumberTable:
        line 385: 0
      LocalVariableTable:
        Start  Length  Slot  Name   Signature
            0       2     0  this   Lcom/windanesz/ancientspellcraft/item/ItemBattlemageShield;
            0       2     1 stack   Lnet/minecraft/item/ItemStack;

  public int func_77619_b();
    descriptor: ()I
    flags: ACC_PUBLIC
    Code:
      stack=1, locals=1, args_size=1
         0: iconst_0
         1: ireturn
      LineNumberTable:
        line 389: 0
      LocalVariableTable:
        Start  Length  Slot  Name   Signature
            0       2     0  this   Lcom/windanesz/ancientspellcraft/item/ItemBattlemageShield;

  public boolean isBookEnchantable(net.minecraft.item.ItemStack, net.minecraft.item.ItemStack);
    descriptor: (Lnet/minecraft/item/ItemStack;Lnet/minecraft/item/ItemStack;)Z
    flags: ACC_PUBLIC
    Code:
      stack=1, locals=3, args_size=3
         0: iconst_0
         1: ireturn
      LineNumberTable:
        line 394: 0
      LocalVariableTable:
        Start  Length  Slot  Name   Signature
            0       2     0  this   Lcom/windanesz/ancientspellcraft/item/ItemBattlemageShield;
            0       2     1 stack   Lnet/minecraft/item/ItemStack;
            0       2     2  book   Lnet/minecraft/item/ItemStack;

  public boolean func_82789_a(net.minecraft.item.ItemStack, net.minecraft.item.ItemStack);
    descriptor: (Lnet/minecraft/item/ItemStack;Lnet/minecraft/item/ItemStack;)Z
    flags: ACC_PUBLIC
    Code:
      stack=1, locals=3, args_size=3
         0: iconst_0
         1: ireturn
      LineNumberTable:
        line 401: 0
      LocalVariableTable:
        Start  Length  Slot  Name   Signature
            0       2     0  this   Lcom/windanesz/ancientspellcraft/item/ItemBattlemageShield;
            0       2     1 toRepair   Lnet/minecraft/item/ItemStack;
            0       2     2 repair   Lnet/minecraft/item/ItemStack;

  public boolean isShield(net.minecraft.item.ItemStack, net.minecraft.entity.EntityLivingBase);
    descriptor: (Lnet/minecraft/item/ItemStack;Lnet/minecraft/entity/EntityLivingBase;)Z
    flags: ACC_PUBLIC
    Code:
      stack=1, locals=3, args_size=3
         0: iconst_1
         1: ireturn
      LineNumberTable:
        line 406: 0
      LocalVariableTable:
        Start  Length  Slot  Name   Signature
            0       2     0  this   Lcom/windanesz/ancientspellcraft/item/ItemBattlemageShield;
            0       2     1 stack   Lnet/minecraft/item/ItemStack;
            0       2     2 entity   Lnet/minecraft/entity/EntityLivingBase;
    RuntimeVisibleParameterAnnotations:
      parameter 0:
      parameter 1:
        0: #214()

  public int getSlotCount();
    descriptor: ()I
    flags: ACC_PUBLIC
    Code:
      stack=1, locals=1, args_size=1
         0: iconst_3
         1: ireturn
      LineNumberTable:
        line 411: 0
      LocalVariableTable:
        Start  Length  Slot  Name   Signature
            0       2     0  this   Lcom/windanesz/ancientspellcraft/item/ItemBattlemageShield;

  public boolean hasGUI();
    descriptor: ()Z
    flags: ACC_PUBLIC
    Code:
      stack=1, locals=1, args_size=1
         0: iconst_1
         1: ireturn
      LineNumberTable:
        line 416: 0
      LocalVariableTable:
        Start  Length  Slot  Name   Signature
            0       2     0  this   Lcom/windanesz/ancientspellcraft/item/ItemBattlemageShield;

  public int getRowCount();
    descriptor: ()I
    flags: ACC_PUBLIC
    Code:
      stack=1, locals=1, args_size=1
         0: iconst_1
         1: ireturn
      LineNumberTable:
        line 421: 0
      LocalVariableTable:
        Start  Length  Slot  Name   Signature
            0       2     0  this   Lcom/windanesz/ancientspellcraft/item/ItemBattlemageShield;

  public int getColumnCount();
    descriptor: ()I
    flags: ACC_PUBLIC
    Code:
      stack=1, locals=1, args_size=1
         0: iconst_3
         1: ireturn
      LineNumberTable:
        line 426: 0
      LocalVariableTable:
        Start  Length  Slot  Name   Signature
            0       2     0  this   Lcom/windanesz/ancientspellcraft/item/ItemBattlemageShield;

  public boolean isItemValid(net.minecraft.item.Item);
    descriptor: (Lnet/minecraft/item/Item;)Z
    flags: ACC_PUBLIC
    Code:
      stack=1, locals=2, args_size=2
         0: iconst_0
         1: ireturn
      LineNumberTable:
        line 431: 0
      LocalVariableTable:
        Start  Length  Slot  Name   Signature
            0       2     0  this   Lcom/windanesz/ancientspellcraft/item/ItemBattlemageShield;
            0       2     1  item   Lnet/minecraft/item/Item;

  static {};
    descriptor: ()V
    flags: ACC_STATIC
    Code:
      stack=1, locals=0, args_size=0
         0: ldc_w         #711                // String 2b5b1f50-b6b5-473a-a402-e45a24d83c13
         3: invokestatic  #717                // Method java/util/UUID.fromString:(Ljava/lang/String;)Ljava/util/UUID;
         6: putstatic     #574                // Field SHIELD_ARMOR_BONUS:Ljava/util/UUID;
         9: ldc_w         #719                // String 3c1acb30-dafb-4c27-a142-680f12ed9c36
        12: invokestatic  #717                // Method java/util/UUID.fromString:(Ljava/lang/String;)Ljava/util/UUID;
        15: putstatic     #721                // Field SHIELD_ARMOR_PERCENT_BONUS:Ljava/util/UUID;
        18: ldc_w         #723                // String 84d9a7e1-5346-4073-98e9-0e04d6d28da5
        21: invokestatic  #717                // Method java/util/UUID.fromString:(Ljava/lang/String;)Ljava/util/UUID;
        24: putstatic     #594                // Field SHIELD_TOUGHNESS_BONUS:Ljava/util/UUID;
        27: return
      LineNumberTable:
        line 60: 0
        line 61: 9
        line 62: 18
}
InnerClasses:
     #15; //class com/windanesz/ancientspellcraft/item/ItemBattlemageShield$1
     public static #20= #17 of #19; //Post=class electroblob/wizardry/event/SpellCastEvent$Post of class electroblob/wizardry/event/SpellCastEvent
     public static #25= #22 of #24; //Message=class electroblob/wizardry/packet/PacketCastSpell$Message of class electroblob/wizardry/packet/PacketCastSpell
     public static #30= #27 of #29; //GeneralSettings=class com/windanesz/ancientspellcraft/Settings$GeneralSettings of class com/windanesz/ancientspellcraft/Settings
     public static final #35= #32 of #34; //ArmourClass=class electroblob/wizardry/item/ItemWizardArmour$ArmourClass of class electroblob/wizardry/item/ItemWizardArmour
     public static final #38= #37 of #19; //Source=class electroblob/wizardry/event/SpellCastEvent$Source of class electroblob/wizardry/event/SpellCastEvent
SourceFile: "ItemBattlemageShield.java"
